Workbook
Name aaa: #REF!
Name aaa: #REF!
Name aaa: #REF!
Name Anniversaire: #REF!,#REF!,#REF!,#REF!
Name Anniversaire: #REF!,#REF!,#REF!,#REF!
Name Anniversaire: #REF!,#REF!,#REF!,#REF!
Name bOH: #REF!,#REF!,#REF!,#REF!
Name bOH: #REF!,#REF!,#REF!,#REF!
Name bOH: #REF!,#REF!,#REF!,#REF!
Name CAP1E: #REF!
Name CAP1E: #REF!
Name CAP1E: #REF!
Name CapitFIXE: #REF!
Name CapitFIXE: #REF!
Name CapitFIXE: #REF!
Name CCC: #REF!
Name CCC: #REF!
Name CCC: #REF!
Name Changement_de_taux: #REF!
Name Changement_de_taux: #REF!
Name Changement_de_taux: #REF!
Name Cout_Total: #REF!
Name Cout_Total: #REF!
Name Cout_Total: #REF!
Name DATDB: #REF!
Name DATDB: #REF!
Name DATDB: #REF!
Name DebAmort: #REF!
Name DebAmort: #REF!
Name DebAmort: #REF!
Name Début_échéance: #REF!
Name Début_échéance: #REF!
Name Début_échéance: #REF!
Name Dernière_période: #REF!
Name Dernière_période: #REF!
Name Dernière_période: #REF!
Name Différé: #REF!
Name Différé: #REF!
Name Différé: #REF!
Name DiffSimple: #REF!
Name DiffSimple: #REF!
Name DiffSimple: #REF!
Name DiffTotal: #REF!
Name DiffTotal: #REF!
Name DiffTotal: #REF!
Name Durée: #REF!
Name Durée: #REF!
Name Durée: #REF!
Name EchFIXE: #REF!
Name EchFIXE: #REF!
Name EchFIXE: #REF!
Name FraisF: #REF!
Name FraisF: #REF!
Name FraisF: #REF!
Name FraisV: #REF!
Name FraisV: #REF!
Name FraisV: #REF!
Name Ijour: #REF!
Name Ijour: #REF!
Name Ijour: #REF!

Sheet Conta corrente
D2: SOMBRA RESORT BRASIL | F2: 48649-3 | H2: 43.730.206/0001-80 | I2: CNPJ
C4: R$ | D4: C/C Ordinario | F4: Banco do Brasil - Goianinha | I4: 1066-9
A5: Nr | B5: Date Comptable | C5: Anno | D5: Description | E5: E/U | F5: CATEGORIA | G5: TIPO | H5: Soggetto | I5: Total | J5: Solde
A6: 1 | B6: 44538 | C6: =IF(B6="","",YEAR(B6)) -> 2021 | D6: saldo anterior | I6: 0 | J6: =I6 -> 0
A7: =A6+1 -> 2 | B7: 44552 | C7: =IF(B7="","",YEAR(B7)) -> 2021 | D7: Pagamento contratto affitto | E7: ENTRADAS | F7: LOCACAO | G7: Produtos | H7: 140852-6 SCP - JM EMPREENDIMENTOS IMOBILIARIO SCP LTDA | I7: 600000 | J7: =IF(I7="",".",J6+I7) -> 600000
A8: =A7+1 -> 3 | B8: 44553 | C8: =IF(B8="","",YEAR(B8)) -> 2021 | D8: Aplicaçao | F8: INVESTIMENTOS | G8: Aplicaçao | H8: B.B. | I8: -600000 | J8: =IF(I8="",".",J7+I8) -> 0
A9: =A8+1 -> 4 | B9: 44558 | C9: =IF(B9="","",YEAR(B9)) -> 2021 | D9: Resgate | F9: INVESTIMENTOS | G9: Resgate | H9: B.B. | I9: 600000 | J9: =IF(I9="",".",J8+I9) -> 600000
A10: =A9+1 -> 5 | B10: 44558 | C10: =IF(B10="","",YEAR(B10)) -> 2021 | D10: Pagamento terreno | E10: SAIDAS | F10: IMOBILIZACAO | G10: Terreno | H10: SOMBRA FLORESTA | I10: -600000 | J10: =IF(I10="",".",J9+I10) -> 0
A11: =A10+1 -> 6 | B11: 44566 | C11: =IF(B11="","",YEAR(B11)) -> 2022 | D11: Resgate | F11: INVESTIMENTOS | G11: Resgate | H11: B.B. | I11: 60 | J11: =IF(I11="",".",J10+I11) -> 60
A12: =A11+1 -> 7 | B12: 44566 | C12: =IF(B12="","",YEAR(B12)) -> 2022 | D12: Tarifa Pacote de Serviços | E12: SAIDAS | F12: DESPESAS FINANCEIRAS | G12: Despesas Bancarias | H12: B.B. | I12: -60 | J12: =IF(I12="",".",J11+I12) -> 0
A13: =A12+1 -> 8 | B13: 44599 | C13: =IF(B13="","",YEAR(B13)) -> 2022 | D13: Tarifa Pacote de Serviços | E13: SAIDAS | F13: DESPESAS FINANCEIRAS | G13: Despesas Bancarias | H13: B.B. | I13: -10.82 | J13: =IF(I13="",".",J12+I13) -> -10.82
A14: =A13+1 -> 9 | B14: 44599 | C14: =IF(B14="","",YEAR(B14)) -> 2022 | D14: Resgate | F14: INVESTIMENTOS | G14: Resgate | H14: B.B. | I14: 10.82 | J14: =IF(I14="",".",J13+I14) -> 0
A15: =A14+1 -> 10 | B15: 44607 | C15: =IF(B15="","",YEAR(B15)) -> 2022 | D15: Pagamento contratto affitto | E15: ENTRADAS | F15: LOCACAO | G15: Produtos | H15: 140850-X - JM EMPREENDIMENTOS IMOB | I15: 183947.11 | J15: =IF(I15="",".",J14+I15) -> 183947.11
A16: =A15+1 -> 11 | B16: 44607 | C16: =IF(B16="","",YEAR(B16)) -> 2022 | D16: Tarifa Pacote de Serviços | E16: SAIDAS | F16: DESPESAS FINANCEIRAS | G16: Despesas Bancarias | H16: B.B. | I16: -55.18 | J16: =IF(I16="",".",J15+I16) -> 183891.93
A17: =A16+1 -> 12 | B17: 44608 | C17: =IF(B17="","",YEAR(B17)) -> 2022 | D17: Pagamento contratto affitto | E17: ENTRADAS | F17: LOCACAO | G17: Produtos | H17: 140850-X - JM EMPREENDIMENTOS IMOB | I17: 200000 | J17: =IF(I17="",".",J16+I17) -> 383891.93
A18: =A17+1 -> 13 | B18: 44609 | C18: =IF(B18="","",YEAR(B18)) -> 2022 | D18: Pagamento contratto affitto | E18: ENTRADAS | F18: LOCACAO | G18: Produtos | H18: 140850-X - JM EMPREENDIMENTOS IMOB | I18: 200000 | J18: =IF(I18="",".",J17+I18) -> 583891.93 | K18: -72.87 | L18: Taxa de localizaçao 2021
A19: =A18+1 -> 14 | B19: 44627 | C19: =IF(B19="","",YEAR(B19)) -> 2022 | D19: Tarifa Pacote de Serviços | E19: SAIDAS | F19: DESPESAS FINANCEIRAS | G19: Despesas Bancarias | H19: B.B. | I19: -66 | J19: =IF(I19="",".",J18+I19) -> 583825.93 | K19: -320.78 | L19: Taxa de localizaçao 2022
A20: =A19+1 -> 15 | B20: 44630 | C20: =IF(B20="","",YEAR(B20)) -> 2022 | D20: Impostos e Taxas | E20: SAIDAS | F20: DESPESAS TRIBUTARIAS | G20: Taxa de Localizaçao 2021 | H20: PREF MUNICIPAL DE NATAL | I20: -72.87 | J20: =IF(I20="",".",J19+I20) -> 583753.06 | K20: =SUM(K18:K19) -> -393.65
A21: =A20+1 -> 16 | B21: 44631 | C21: =IF(B21="","",YEAR(B21)) -> 2022 | D21: Impostos e Taxas | E21: SAIDAS | F21: DESPESAS TRIBUTARIAS | G21: Taxa de Localizaçao 2022 | H21: PREF MUNICIPAL DE NATAL | I21: -320.78 | J21: =IF(I21="",".",J20+I21) -> 583432.28 | K21: -23.37 | L21: Juros e multa
A22: =A21+1 -> 17 | B22: 44632 | C22: =IF(B22="","",YEAR(B22)) -> 2022 | D22: Impostos e Taxas | E22: SAIDAS | F22: DESPESAS TRIBUTARIAS | G22: Juros e Multa | H22: PREF MUNICIPAL DE NATAL | I22: -23.37 | J22: =IF(I22="",".",J21+I22) -> 583408.91 | K22: =SUM(K20:K21) -> -417.02
A23: =A22+1 -> 18 | B23: 44656 | C23: =IF(B23="","",YEAR(B23)) -> 2022 | D23: Tarifa Pacote de Serviços | E23: SAIDAS | F23: DESPESAS FINANCEIRAS | G23: Despesas Bancarias | H23: B.B. | I23: -66 | J23: =IF(I23="",".",J22+I23) -> 583342.91
A24: =A23+1 -> 19 | B24: 44686 | C24: =IF(B24="","",YEAR(B24)) -> 2022 | D24: Tarifa Pacote de Serviços | E24: SAIDAS | F24: DESPESAS FINANCEIRAS | G24: Despesas Bancarias | H24: B.B. | I24: -66 | J24: =IF(I24="",".",J23+I24) -> 583276.91
A25: =A24+1 -> 20 | B25: 44718 | C25: =IF(B25="","",YEAR(B25)) -> 2022 | D25: Tarifa Pacote de Serviços | E25: SAIDAS | F25: DESPESAS FINANCEIRAS | G25: Despesas Bancarias | H25: B.B. | I25: -66 | J25: =IF(I25="",".",J24+I25) -> 583210.91
A26: =A25+1 -> 21 | B26: 44735 | C26: =IF(B26="","",YEAR(B26)) -> 2022 | D26: Aplicaçao | F26: INVESTIMENTOS | G26: Aplicaçao | H26: B.B. | I26: -583210.91 | J26: =IF(I26="",".",J25+I26) -> -1.1641532e-10
A27: =A26+1 -> 22 | B27: 44748 | C27: =IF(B27="","",YEAR(B27)) -> 2022 | D27: Tarifa Pacote de Serviços | E27: SAIDAS | F27: DESPESAS FINANCEIRAS | G27: Despesas Bancarias | H27: B.B. | I27: -66 | J27: =IF(I27="",".",J26+I27) -> -66
A28: =A27+1 -> 23 | B28: 44748 | C28: =IF(B28="","",YEAR(B28)) -> 2022 | D28: Resgate | F28: INVESTIMENTOS | G28: Resgate | H28: B.B. | I28: 66 | J28: =IF(I28="",".",J27+I28) -> -1.1641532e-10
A29: =A28+1 -> 24 | B29: 44778 | C29: =IF(B29="","",YEAR(B29)) -> 2022 | D29: Tarifa Pacote de Serviços | E29: SAIDAS | F29: DESPESAS FINANCEIRAS | G29: Despesas Bancarias | H29: B.B. | I29: -66 | J29: =IF(I29="",".",J28+I29) -> -66
A30: =A29+1 -> 25 | B30: 44778 | C30: =IF(B30="","",YEAR(B30)) -> 2022 | D30: Resgate | F30: INVESTIMENTOS | G30: Resgate | H30: B.B. | I30: 66 | J30: =IF(I30="",".",J29+I30) -> -1.1641532e-10
A31: =A30+1 -> 26 | B31: 44809 | C31: =IF(B31="","",YEAR(B31)) -> 2022 | D31: Tarifa Pacote de Serviços | E31: SAIDAS | F31: DESPESAS FINANCEIRAS | G31: Despesas Bancarias | H31: B.B. | I31: -66 | J31: =IF(I31="",".",J30+I31) -> -66
A32: =A31+1 -> 27 | B32: 44809 | C32: =IF(B32="","",YEAR(B32)) -> 2022 | D32: Resgate | F32: INVESTIMENTOS | G32: Resgate | H32: B.B. | I32: 66 | J32: =IF(I32="",".",J31+I32) -> -1.1641532e-10
A33: =A32+1 -> 28 | B33: 44839 | C33: =IF(B33="","",YEAR(B33)) -> 2022 | D33: Tarifa Pacote de Serviços | E33: SAIDAS | F33: DESPESAS FINANCEIRAS | G33: Despesas Bancarias | H33: B.B. | I33: -66 | J33: =IF(I33="",".",J32+I33) -> -66
A34: =A33+1 -> 29 | B34: 44839 | C34: =IF(B34="","",YEAR(B34)) -> 2022 | D34: Resgate | F34: INVESTIMENTOS | G34: Resgate | H34: B.B. | I34: 66 | J34: =IF(I34="",".",J33+I34) -> -1.1641532e-10
A35: =A34+1 -> 30 | B35: 44872 | C35: =IF(B35="","",YEAR(B35)) -> 2022 | D35: Tarifa Pacote de Serviços | E35: SAIDAS | F35: DESPESAS FINANCEIRAS | G35: Despesas Bancarias | H35: B.B. | I35: -66 | J35: =IF(I35="",".",J34+I35) -> -66
A36: =A35+1 -> 31 | B36: 44872 | C36: =IF(B36="","",YEAR(B36)) -> 2022 | D36: Resgate | F36: INVESTIMENTOS | G36: Resgate | H36: B.B. | I36: 66 | J36: =IF(I36="",".",J35+I36) -> -1.1641532e-10
A37: =A36+1 -> 32 | B37: 44900 | C37: =IF(B37="","",YEAR(B37)) -> 2022 | D37: Tarifa Pacote de Serviços | E37: SAIDAS | F37: DESPESAS FINANCEIRAS | G37: Despesas Bancarias | H37: B.B. | I37: -66 | J37: =IF(I37="",".",J36+I37) -> -66
A38: =A37+1 -> 33 | B38: 44900 | C38: =IF(B38="","",YEAR(B38)) -> 2022 | D38: Resgate | F38: INVESTIMENTOS | G38: Resgate | H38: B.B. | I38: 66 | J38: =IF(I38="",".",J37+I38) -> -1.1641532e-10
A39: =A38+1 -> 34 | B39: 44918 | C39: =IF(B39="","",YEAR(B39)) -> 2022 | D39: 50% Traduzione giurata dello Statuto | E39: SAIDAS | F39: DESPESAS GERAIS | G39: Varias | H39: Antonio Francisco Alves Ro | I39: -1050 | J39: =IF(I39="",".",J38+I39) -> -1050
A40: =A39+1 -> 35 | B40: 44918 | C40: =IF(B40="","",YEAR(B40)) -> 2022 | D40: Resgate | F40: INVESTIMENTOS | G40: Resgate | H40: B.B. | I40: 1050 | J40: =IF(I40="",".",J39+I40) -> -1.1641532e-10
A41: =A40+1 -> 36 | B41: 44924 | C41: =IF(B41="","",YEAR(B41)) -> 2022 | D41: Pagamento contratto affitto | E41: ENTRADAS | F41: LOCACAO | G41: Produtos | H41: 140852-6 SCP - JM EMPREENDIMENTOS IMOBILIARIO SCP LTDA | I41: 255109.77 | J41: =IF(I41="",".",J40+I41) -> 255109.77
A42: =A41+1 -> 37 | B42: 44931 | C42: =IF(B42="","",YEAR(B42)) -> 2023 | D42: Tarifa Pacote de Serviços | E42: SAIDAS | F42: DESPESAS FINANCEIRAS | G42: Despesas Bancarias | H42: B.B. | I42: -69 | J42: =IF(I42="",".",J41+I42) -> 255040.77
A43: =A42+1 -> 38 | B43: 44958 | C43: =IF(B43="","",YEAR(B43)) -> 2023 | D43: Aplicaçao | F43: INVESTIMENTOS | G43: Aplicaçao | H43: B.B. | I43: -255040.77 | J43: =IF(I43="",".",J42+I43) -> -1.1641532e-10
A44: =A43+1 -> 39 | B44: 44963 | C44: =IF(B44="","",YEAR(B44)) -> 2023 | D44: Tarifa Pacote de Serviços | E44: SAIDAS | F44: DESPESAS FINANCEIRAS | G44: Despesas Bancarias | H44: B.B. | I44: -69 | J44: =IF(I44="",".",J43+I44) -> -69
A45: =A44+1 -> 40 | B45: 44963 | C45: =IF(B45="","",YEAR(B45)) -> 2023 | D45: Resgate | F45: INVESTIMENTOS | G45: Resgate | H45: B.B. | I45: 69 | J45: =IF(I45="",".",J44+I45) -> -1.1641532e-10
A46: =A45+1 -> 41 | B46: 44991 | C46: =IF(B46="","",YEAR(B46)) -> 2023 | D46: Tarifa Pacote de Serviços | E46: SAIDAS | F46: DESPESAS FINANCEIRAS | G46: Despesas Bancarias | H46: B.B. | I46: -69 | J46: =IF(I46="",".",J45+I46) -> -69
A47: =A46+1 -> 42 | B47: 44991 | C47: =IF(B47="","",YEAR(B47)) -> 2023 | D47: Resgate | F47: INVESTIMENTOS | G47: Resgate | H47: B.B. | I47: 69 | J47: =IF(I47="",".",J46+I47) -> -1.1641532e-10
A48: =A47+1 -> 43 | B48: 45022 | C48: =IF(B48="","",YEAR(B48)) -> 2023 | D48: Tarifa Pacote de Serviços | E48: SAIDAS | F48: DESPESAS FINANCEIRAS | G48: Despesas Bancarias | H48: B.B. | I48: -69 | J48: =IF(I48="",".",J47+I48) -> -69
A49: =A48+1 -> 44 | B49: 45022 | C49: =IF(B49="","",YEAR(B49)) -> 2023 | D49: Resgate | F49: INVESTIMENTOS | G49: Resgate | H49: B.B. | I49: 69 | J49: =IF(I49="",".",J48+I49) -> -1.1641532e-10
A50: =A49+1 -> 45 | B50: 45051 | C50: =IF(B50="","",YEAR(B50)) -> 2023 | D50: Tarifa Pacote de Serviços | E50: SAIDAS | F50: DESPESAS FINANCEIRAS | G50: Despesas Bancarias | H50: B.B. | I50: -69 | J50: =IF(I50="",".",J49+I50) -> -69
A51: =A50+1 -> 46 | B51: 45051 | C51: =IF(B51="","",YEAR(B51)) -> 2023 | D51: Resgate | F51: INVESTIMENTOS | G51: Resgate | H51: B.B. | I51: 69 | J51: =IF(I51="",".",J50+I51) -> -1.1641532e-10
A52: =A51+1 -> 47 | B52: 45077 | C52: =IF(B52="","",YEAR(B52)) -> 2023 | D52: Domiciliazione societaria | E52: SAIDAS | F52: DESPESAS GERAIS | G52: Varias | H52: ONE Empreendimentos Serviços | I52: -850 | J52: =IF(I52="",".",J51+I52) -> -850
A53: =A52+1 -> 48 | B53: 45077 | C53: =IF(B53="","",YEAR(B53)) -> 2023 | D53: Resgate | F53: INVESTIMENTOS | G53: Resgate | H53: B.B. | I53: 850 | J53: =IF(I53="",".",J52+I53) -> -1.1641532e-10
A54: =A53+1 -> 49 | B54: 45082 | C54: =IF(B54="","",YEAR(B54)) -> 2023 | D54: Tarifa Pacote de Serviços | E54: SAIDAS | F54: DESPESAS FINANCEIRAS | G54: Despesas Bancarias | H54: B.B. | I54: -69 | J54: =IF(I54="",".",J53+I54) -> -69
A55: =A54+1 -> 50 | B55: 45082 | C55: =IF(B55="","",YEAR(B55)) -> 2023 | D55: Resgate | F55: INVESTIMENTOS | G55: Resgate | H55: B.B. | I55: 69 | J55: =IF(I55="",".",J54+I55) -> -1.1641532e-10
A56: =A55+1 -> 51 | B56: 45112 | C56: =IF(B56="","",YEAR(B56)) -> 2023 | D56: Tarifa Pacote de Serviços | E56: SAIDAS | F56: DESPESAS FINANCEIRAS | G56: Despesas Bancarias | H56: B.B. | I56: -69 | J56: =IF(I56="",".",J55+I56) -> -69
A57: =A56+1 -> 52 | B57: 45112 | C57: =IF(B57="","",YEAR(B57)) -> 2023 | D57: Resgate | F57: INVESTIMENTOS | G57: Resgate | H57: B.B. | I57: 69 | J57: =IF(I57="",".",J56+I57) -> -1.1641532e-10
A58: =A57+1 -> 53 | B58: 45124 | C58: =IF(B58="","",YEAR(B58)) -> 2023 | D58: Cambiamento indirizzo societario | E58: SAIDAS | F58: DESPESAS GERAIS | G58: Varias | H58: Igor R.R. Franca Sociedade - Junta Comercial | I58: -1200 | J58: =IF(I58="",".",J57+I58) -> -1200
A59: =A58+1 -> 54 | B59: 45124 | C59: =IF(B59="","",YEAR(B59)) -> 2023 | D59: Resgate | F59: INVESTIMENTOS | G59: Resgate | H59: B.B. | I59: 1200 | J59: =IF(I59="",".",J58+I59) -> -1.1641532e-10
A60: =A59+1 -> 55 | B60: 45145 | C60: =IF(B60="","",YEAR(B60)) -> 2023 | D60: Tarifa Pacote de Serviços | E60: SAIDAS | F60: DESPESAS FINANCEIRAS | G60: Despesas Bancarias | H60: B.B. | I60: -69 | J60: =IF(I60="",".",J59+I60) -> -69
A61: =A60+1 -> 56 | B61: 45145 | C61: =IF(B61="","",YEAR(B61)) -> 2023 | D61: Resgate | F61: INVESTIMENTOS | G61: Resgate | H61: B.B. | I61: 69 | J61: =IF(I61="",".",J60+I61) -> -1.1641532e-10
A62: =A61+1 -> 57 | B62: 45174 | C62: =IF(B62="","",YEAR(B62)) -> 2023 | D62: Tarifa Pacote de Serviços | E62: SAIDAS | F62: DESPESAS FINANCEIRAS | G62: Despesas Bancarias | H62: B.B. | I62: -69 | J62: =IF(I62="",".",J61+I62) -> -69
A63: =A62+1 -> 58 | B63: 45174 | C63: =IF(B63="","",YEAR(B63)) -> 2023 | D63: Resgate | F63: INVESTIMENTOS | G63: Resgate | H63: B.B. | I63: 69 | J63: =IF(I63="",".",J62+I63) -> -1.1641532e-10
A64: =A63+1 -> 59 | B64: 45204 | C64: =IF(B64="","",YEAR(B64)) -> 2023 | D64: Tarifa Pacote de Serviços | E64: SAIDAS | F64: DESPESAS FINANCEIRAS | G64: Despesas Bancarias | H64: B.B. | I64: -69 | J64: =IF(I64="",".",J63+I64) -> -69
A65: =A64+1 -> 60 | B65: 45204 | C65: =IF(B65="","",YEAR(B65)) -> 2023 | D65: Resgate | F65: INVESTIMENTOS | G65: Resgate | H65: B.B. | I65: 69 | J65: =IF(I65="",".",J64+I65) -> -1.1641532e-10
A66: =A65+1 -> 61 | B66: 45236 | C66: =IF(B66="","",YEAR(B66)) -> 2023 | D66: Tarifa Pacote de Serviços | E66: SAIDAS | F66: DESPESAS FINANCEIRAS | G66: Despesas Bancarias | H66: B.B. | I66: -69 | J66: =IF(I66="",".",J65+I66) -> -69
A67: =A66+1 -> 62 | B67: 45236 | C67: =IF(B67="","",YEAR(B67)) -> 2023 | D67: Resgate | F67: INVESTIMENTOS | G67: Resgate | H67: B.B. | I67: 69 | J67: =IF(I67="",".",J66+I67) -> -1.1641532e-10
A68: =A67+1 -> 63 | B68: 45265 | C68: =IF(B68="","",YEAR(B68)) -> 2023 | D68: Tarifa Pacote de Serviços | E68: SAIDAS | F68: DESPESAS FINANCEIRAS | G68: Despesas Bancarias | H68: B.B. | I68: -72 | J68: =IF(I68="",".",J67+I68) -> -72
A69: =A68+1 -> 64 | B69: 45265 | C69: =IF(B69="","",YEAR(B69)) -> 2023 | D69: Resgate | F69: INVESTIMENTOS | G69: Resgate | H69: B.B. | I69: 72 | J69: =IF(I69="",".",J68+I69) -> -1.1641532e-10
A70: =A69+1 -> 65 | B70: 45296 | C70: =IF(B70="","",YEAR(B70)) -> 2024 | D70: Tarifa Pacote de Serviços | E70: SAIDAS | F70: DESPESAS FINANCEIRAS | G70: Despesas Bancarias | H70: B.B. | I70: -72 | J70: =IF(I70="",".",J69+I70) -> -72
A71: =A70+1 -> 66 | B71: 45296 | C71: =IF(B71="","",YEAR(B71)) -> 2024 | D71: Resgate | F71: INVESTIMENTOS | G71: Resgate | H71: B.B. | I71: 72 | J71: =IF(I71="",".",J70+I71) -> -1.1641532e-10
A72: =A71+1 -> 67 | B72: 45385 | C72: =IF(B72="","",YEAR(B72)) -> 2024 | D72: Impostos e Taxas | E72: SAIDAS | F72: DESPESAS TRIBUTARIAS | G72: Taxa de Localizaçao 2023 | H72: PREF MUNICIPAL DE NATAL | I72: -408.82 | J72: =IF(I72="",".",J71+I72) -> -408.82
A73: =A72+1 -> 68 | B73: 45385 | C73: =IF(B73="","",YEAR(B73)) -> 2024 | D73: Taxa de Localizaçao | E73: SAIDAS | F73: DESPESAS TRIBUTARIAS | G73: Taxa de Localizaçao 2024 | H73: PREF MUNICIPAL DE NATAL | I73: -408.78 | J73: =IF(I73="",".",J72+I73) -> -817.6
A74: =A73+1 -> 69 | B74: 45385 | C74: =IF(B74="","",YEAR(B74)) -> 2024 | D74: Resgate | F74: INVESTIMENTOS | G74: Resgate | H74: B.B. | I74: 817.6 | J74: =IF(I74="",".",J73+I74) -> -1.1630163e-10
A75: =A74+1 -> 70 | B75: 45387 | C75: =IF(B75="","",YEAR(B75)) -> 2024 | D75: Tarifa Pacote de Serviços | E75: SAIDAS | F75: DESPESAS FINANCEIRAS | G75: Despesas Bancarias | H75: B.B. | I75: -72 | J75: =IF(I75="",".",J74+I75) -> -72
A76: =A75+1 -> 71 | B76: 45387 | C76: =IF(B76="","",YEAR(B76)) -> 2024 | D76: Resgate | F76: INVESTIMENTOS | G76: Resgate | H76: B.B. | I76: 72 | J76: =IF(I76="",".",J75+I76) -> -1.1630163e-10
A77: =A76+1 -> 72 | B77: 45418 | C77: =IF(B77="","",YEAR(B77)) -> 2024 | D77: Tarifa Pacote de Serviços | E77: SAIDAS | F77: DESPESAS FINANCEIRAS | G77: Despesas Bancarias | H77: B.B. | I77: -72 | J77: =IF(I77="",".",J76+I77) -> -72
A78: =A77+1 -> 73 | B78: 45418 | C78: =IF(B78="","",YEAR(B78)) -> 2024 | D78: Resgate | F78: INVESTIMENTOS | G78: Resgate | H78: B.B. | I78: 72 | J78: =IF(I78="",".",J77+I78) -> -1.1630163e-10
A79: =A78+1 -> 74 | B79: 45441 | C79: =IF(B79="","",YEAR(B79)) -> 2024 | D79: Spese Cartorio | E79: SAIDAS | F79: DESPESAS GERAIS | G79: Varias | H79: Natal - Cartorio 2 Oficio Nota | I79: -1049.08 | J79: =IF(I79="",".",J78+I79) -> -1049.08
A80: =A79+1 -> 75 | B80: 45441 | C80: =IF(B80="","",YEAR(B80)) -> 2024 | D80: Resgate | F80: INVESTIMENTOS | G80: Resgate | H80: B.B. | I80: 1049.08 | J80: =IF(I80="",".",J79+I80) -> -1.1641532e-10
A81: =A80+1 -> 76 | B81: 45448 | C81: =IF(B81="","",YEAR(B81)) -> 2024 | D81: Tarifa Pacote de Serviços | E81: SAIDAS | F81: DESPESAS FINANCEIRAS | G81: Despesas Bancarias | H81: B.B. | I81: -72 | J81: =IF(I81="",".",J80+I81) -> -72
A82: =A81+1 -> 77 | B82: 45448 | C82: =IF(B82="","",YEAR(B82)) -> 2024 | D82: Resgate | F82: INVESTIMENTOS | G82: Resgate | H82: B.B. | I82: 72 | J82: =IF(I82="",".",J81+I82) -> -1.1641532e-10
A83: =A82+1 -> 78 | B83: 45478 | C83: =IF(B83="","",YEAR(B83)) -> 2024 | D83: Domiciliazione societaria | E83: SAIDAS | F83: DESPESAS GERAIS | G83: Varias | H83: ONE Empreendimentos Serviços | I83: -850 | J83: =IF(I83="",".",J82+I83) -> -850
A84: =A83+1 -> 79 | B84: 45478 | C84: =IF(B84="","",YEAR(B84)) -> 2024 | D84: Tarifa Pacote de Serviços | E84: SAIDAS | F84: DESPESAS FINANCEIRAS | G84: Despesas Bancarias | H84: B.B. | I84: -72 | J84: =IF(I84="",".",J83+I84) -> -922
A85: =A84+1 -> 80 | B85: 45478 | C85: =IF(B85="","",YEAR(B85)) -> 2024 | D85: Resgate | F85: INVESTIMENTOS | G85: Resgate | H85: B.B. | I85: 922 | J85: =IF(I85="",".",J84+I85) -> -1.1641532e-10
A86: =A85+1 -> 81 | B86: 45509 | C86: =IF(B86="","",YEAR(B86)) -> 2024 | D86: Tarifa Pacote de Serviços | E86: SAIDAS | F86: DESPESAS FINANCEIRAS | G86: Despesas Bancarias | H86: B.B. | I86: -73.8 | J86: =IF(I86="",".",J85+I86) -> -73.8
A87: =A86+1 -> 82 | B87: 45509 | C87: =IF(B87="","",YEAR(B87)) -> 2024 | D87: Resgate | F87: INVESTIMENTOS | G87: Resgate | H87: B.B. | I87: 73.8 | J87: =IF(I87="",".",J86+I87) -> -1.1641532e-10
A88: =A87+1 -> 83 | B88: 45540 | C88: =IF(B88="","",YEAR(B88)) -> 2024 | D88: Tarifa Pacote de Serviços | E88: SAIDAS | F88: DESPESAS FINANCEIRAS | G88: Despesas Bancarias | H88: B.B. | I88: -73.8 | J88: =IF(I88="",".",J87+I88) -> -73.8
A89: =A88+1 -> 84 | B89: 45540 | C89: =IF(B89="","",YEAR(B89)) -> 2024 | D89: Resgate | F89: INVESTIMENTOS | G89: Resgate | H89: B.B. | I89: 73.8 | J89: =IF(I89="",".",J88+I89) -> -1.1641532e-10
A90: =A89+1 -> 85 | B90: 45572 | C90: =IF(B90="","",YEAR(B90)) -> 2024 | D90: Tarifa Pacote de Serviços | E90: SAIDAS | F90: DESPESAS FINANCEIRAS | G90: Despesas Bancarias | H90: B.B. | I90: -73.8 | J90: =IF(I90="",".",J89+I90) -> -73.8
A91: =A90+1 -> 86 | B91: 45572 | C91: =IF(B91="","",YEAR(B91)) -> 2024 | D91: Resgate | F91: INVESTIMENTOS | G91: Resgate | H91: B.B. | I91: 73.8 | J91: =IF(I91="",".",J90+I91) -> -1.1641532e-10
A92: =A91+1 -> 87 | B92: 45596 | C92: =IF(B92="","",YEAR(B92)) -> 2024 | D92: Spese Cartorio | E92: SAIDAS | F92: DESPESAS GERAIS | G92: Gestao Empresarial | H92: Essencial Gestao Empresarial LTDA | I92: -184 | J92: =IF(I92="",".",J91+I92) -> -184
A93: =A92+1 -> 88 | B93: 45596 | C93: =IF(B93="","",YEAR(B93)) -> 2024 | D93: Resgate | F93: INVESTIMENTOS | G93: Resgate | H93: B.B. | I93: 184 | J93: =IF(I93="",".",J92+I93) -> -1.1641532e-10
A94: =A93+1 -> 89 | B94: 45601 | C94: =IF(B94="","",YEAR(B94)) -> 2024 | D94: Tarifa Pacote de Serviços | E94: SAIDAS | F94: DESPESAS FINANCEIRAS | G94: Despesas Bancarias | H94: B.B. | I94: -73.8 | J94: =IF(I94="",".",J93+I94) -> -73.8
A95: =A94+1 -> 90 | B95: 45601 | C95: =IF(B95="","",YEAR(B95)) -> 2024 | D95: Resgate | F95: INVESTIMENTOS | G95: Resgate | H95: B.B. | I95: 73.8 | J95: =IF(I95="",".",J94+I95) -> -1.1641532e-10
A96: =A95+1 -> 91 | B96: 45603 | C96: =IF(B96="","",YEAR(B96)) -> 2024 | D96: Compra de Madeira | E96: SAIDAS | F96: DESPESAS GERAIS | G96: Varias | H96: Mac Madeira Ltd | I96: -421.6 | J96: =IF(I96="",".",J95+I96) -> -421.6
A97: =A96+1 -> 92 | B97: 45603 | C97: =IF(B97="","",YEAR(B97)) -> 2024 | D97: Resgate | F97: INVESTIMENTOS | G97: Resgate | H97: B.B. | I97: 421.6 | J97: =IF(I97="",".",J96+I97) -> -1.1641532e-10
A98: =A97+1 -> 93 | B98: 45625 | C98: =IF(B98="","",YEAR(B98)) -> 2024 | D98: Honorario Contabeis | E98: SAIDAS | F98: DESPESAS GERAIS | G98: Gestao Empresarial | H98: Essencial Gestao Empresarial Ltda | I98: -300 | J98: =IF(I98="",".",J97+I98) -> -300 | K98: Nota 02-2024
A99: =A98+1 -> 94 | B99: 45625 | C99: =IF(B99="","",YEAR(B99)) -> 2024 | D99: Honorario Contabeis | E99: SAIDAS | F99: DESPESAS GERAIS | G99: Gestao Empresarial | H99: LRT Soluçoes Corporativas e Contabeis Ltda | I99: -353 | J99: =IF(I99="",".",J98+I99) -> -653 | K99: Nota 01-2024
A100: =A99+1 -> 95 | B100: 45625 | C100: =IF(B100="","",YEAR(B100)) -> 2024 | D100: Resgate | F100: INVESTIMENTOS | G100: Resgate | H100: B.B. | I100: 653 | J100: =IF(I100="",".",J99+I100) -> -1.1641532e-10
A101: =A100+1 -> 96 | B101: 45631 | C101: =IF(B101="","",YEAR(B101)) -> 2024 | D101: Tarifa Pacote de Serviços | E101: SAIDAS | F101: DESPESAS FINANCEIRAS | G101: Despesas Bancarias | H101: B.B. | I101: -73.8 | J101: =IF(I101="",".",J100+I101) -> -73.8
A102: =A101+1 -> 97 | B102: 45631 | C102: =IF(B102="","",YEAR(B102)) -> 2024 | D102: Resgate | F102: INVESTIMENTOS | G102: Resgate | H102: B.B. | I102: 73.8 | J102: =IF(I102="",".",J101+I102) -> -1.1641532e-10
...

Sheet Resumo BB ORD
A6: Sum of Total | D6: Anno
A7: CATEGORIA | B7: TIPO | C7: Soggetto | D7: 2021 | E7: 2022 | F7: 2023 | G7: 2024 | H7: 2025 | I7: 2026 | J7: Totale complessivo
A8: INVESTIMENTOS
B9: Aplicaçao
C10: B.B. | D10: -600000 | E10: -583210.91 | F10: -255040.77 | H10: -597295.96 | J10: -2035547.6
B12: Resgate
C13: B.B. | D13: 600000 | E13: 1516.82 | F13: 2812 | G13: 23022.07 | H13: 92862.17 | I13: 12024.75 | J13: 732237.81
A15: LOCACAO
B16: Produtos
C17: 140852-6 SCP - JM EMPREENDIMENTOS IMOBILIARIO SCP LTDA | D17: 600000 | E17: 255109.77 | H17: 617509.26 | I17: 43156.04 | J17: 1515775.1
C18: 140850-X - JM EMPREENDIMENTOS IMOB | E18: 583947.11 | J18: 583947.11
A20: IMOBILIZACAO
B21: Terreno
C22: SOMBRA FLORESTA | D22: -600000 | J22: -600000
A24: DESPESAS FINANCEIRAS
B25: Despesas Bancarias
C26: B.B. | E26: -786 | F26: -831 | G26: -729 | H26: -925.6 | I26: -791.1 | J26: -4062.7
A28: DESPESAS TRIBUTARIAS
B29: Juros e Multa
C30: PREF MUNICIPAL DE NATAL | E30: -23.37 | J30: -23.37
B32: Taxa de Localizaçao 2021
C33: PREF MUNICIPAL DE NATAL | E33: -72.87 | J33: -72.87
B35: Taxa de Localizaçao 2022
C36: PREF MUNICIPAL DE NATAL | E36: -320.78 | J36: -320.78
B38: Taxa de Localizaçao 2023
C39: PREF MUNICIPAL DE NATAL | G39: -408.82 | J39: -408.82
B41: Taxa de Localizaçao 2024
C42: PREF MUNICIPAL DE NATAL | G42: -408.78 | J42: -408.78
B44: Taxa de Localizaçao 2025
C45: PREF MUNICIPAL DE NATAL | H45: -378.61 | J45: -378.61
B47: Taxa de Localizaçao 2026
C48: PREF MUNICIPAL DE NATAL | I48: -398.75 | J48: -398.75
A50: DESPESAS GERAIS
B51: Varias
C52: Antonio Francisco Alves Ro | E52: -1050 | J52: -1050
C53: ONE Empreendimentos Serviços | F53: -850 | G53: -850 | H53: -898.2 | J53: -2598.2
C54: Igor R.R. Franca Sociedade - Junta Comercial | F54: -1200 | J54: -1200
C55: Natal - Cartorio 2 Oficio Nota | G55: -1049.08 | J55: -1049.08
C56: Mac Madeira Ltd | G56: -421.6 | J56: -421.6
C57: Magnolia Melo de Souza | G57: -3700 | H57: -4800 | J57: -8500
C58: L & M - Varejo da costruçao Elizomar de Lima Marques | G58: -7200 | J58: -7200
C59: Nu Pagamento SA | H59: -88.25 | J59: -88.25
C60: C N Palaoro Eireli | H60: -13337.99 | J60: -13337.99
C61: GLOBAL TECH | G61: -6764.79 | H61: 6764.79 | J61: 0
C62: Comercial Distribuidora Natal | H62: -4809.38 | J62: -4809.38
C63: Seahub Coworking | I63: -935.39 | J63: -935.39
B65: Gestao Empresarial
C66: Essencial Gestao Empresarial LTDA | G66: -1137 | H66: -9556 | I66: -15857 | J66: -26550
C67: LRT Soluçoes Corporativas e Contabeis Ltda | G67: -353 | H67: -2824 | J67: -3177
C68: JJ Assessoria Contabil | H68: -3883 | I68: -3353.31 | J68: -7236.31
C69: LT Soluçoes Corporativas e Contabeis | I69: -1998 | J69: -1998
B71: Moveis Casa H
C72: Butzke Importaçao Exportaçao | H72: -7482.84 | J72: -7482.84
A74: CESSAO DE CREDITO
B75: Cessao de Credito
C76: Franco Toscano | H76: -62000 | J76: -62000
A78: Totale complessivo | D78: 0 | E78: 255109.77 | F78: -255109.77 | G78: 9.094947e-13 | H78: 8856.39 | I78: 31847.24 | J78: 40703.63

Sheet Conto Investimento
D2: SOMBRA RESORT BRASIL | F2: 48649-3 | I2: 43.730.206/0001-80 | J2: CNPJ:
I3: 43.617.343/0001-02 | J3: CNPJ Conta Agil:
C4: R$ | D4: C/C Investimento Fundos | F4: Banco do Brasil - Goianinha | I4: 1066-9
A5: Nr | B5: Date Comptable | C5: Anno | D5: Description | E5: E/U | F5: CATEGORIA | G5: TIPO | H5: Descrizione | I5: Total | J5: Solde
A6: 1 | B6: 44530 | C6: =IF(B6="","",YEAR(B6)) -> 2021 | D6: saldo anterior | I6: 0 | J6: =I6 -> 0
A7: =A6+1 -> 2 | B7: 44553 | C7: =IF(B7="","",YEAR(B7)) -> 2021 | D7: Aplicaçao | F7: INVESTIMENTOS | G7: Aplicaçao | H7: B.B. | I7: 600000 | J7: =IF(I7="",".",J6+I7) -> 600000
A8: =A7+1 -> 3 | B8: 44558 | C8: =IF(B8="","",YEAR(B8)) -> 2021 | D8: Resgate | F8: INVESTIMENTOS | G8: Resgate | H8: B.B. | I8: -600000 | J8: =IF(I8="",".",J7+I8) -> 0
A9: =A8+1 -> 4 | B9: 44561 | C9: =IF(B9="","",YEAR(B9)) -> 2021 | D9: Rendimento Bruto | E9: ENTRADAS | F9: JUROS | G9: Receitas Financeiras | I9: 536.34 | J9: =IF(I9="",".",J8+I9) -> 536.34
A10: =A9+1 -> 5 | B10: 44561 | C10: =IF(B10="","",YEAR(B10)) -> 2021 | D10: Imposto de Renda | E10: SAIDAS | F10: DESPESAS TRIBUTARIAS | G10: IRRF | I10: -20.5 | J10: =IF(I10="",".",J9+I10) -> 515.84
A11: =A10+1 -> 6 | B11: 44561 | C11: =IF(B11="","",YEAR(B11)) -> 2021 | D11: I.O.F. | E11: SAIDAS | F11: DESPESAS TRIBUTARIAS | G11: IOF Bancario | I11: -445.05 | J11: =IF(I11="",".",J10+I11) -> 70.79
A12: =A11+1 -> 7 | B12: 44566 | C12: =IF(B12="","",YEAR(B12)) -> 2022 | D12: Resgate | F12: RESGATE | G12: Despesas Bancarias | H12: B.B. | I12: -60 | J12: =IF(I12="",".",J11+I12) -> 10.79
A13: =A12+1 -> 8 | B13: 44592 | C13: =IF(B13="","",YEAR(B13)) -> 2022 | D13: Rendimento Bruto | E13: ENTRADAS | F13: JUROS | G13: Receitas Financeiras | I13: 0.13 | J13: =IF(I13="",".",J12+I13) -> 10.92
A14: =A13+1 -> 9 | B14: 44592 | C14: =IF(B14="","",YEAR(B14)) -> 2022 | D14: Imposto de Renda | E14: SAIDAS | F14: DESPESAS TRIBUTARIAS | G14: IRRF | I14: -0.01 | J14: =IF(I14="",".",J13+I14) -> 10.91
A15: =A14+1 -> 10 | B15: 44592 | C15: =IF(B15="","",YEAR(B15)) -> 2022 | D15: I.O.F. | E15: SAIDAS | F15: DESPESAS TRIBUTARIAS | G15: IOF Bancario | I15: -0.08 | J15: =IF(I15="",".",J14+I15) -> 10.83
A16: =A15+1 -> 11 | B16: 44599 | C16: =IF(B16="","",YEAR(B16)) -> 2022 | D16: Resgate | F16: RESGATE | G16: Despesas Bancarias | H16: B.B. | I16: -10.82 | J16: =IF(I16="",".",J15+I16) -> 0.01
A17: =A16+1 -> 12 | B17: 44617 | C17: =IF(B17="","",YEAR(B17)) -> 2022 | D17: Rendimento Bruto | E17: ENTRADAS | F17: JUROS | G17: Receitas Financeiras | I17: 0.01 | J17: =IF(I17="",".",J16+I17) -> 0.02
A18: =A17+1 -> 13 | B18: 44617 | C18: =IF(B18="","",YEAR(B18)) -> 2022 | D18: Imposto de Renda | E18: SAIDAS | F18: DESPESAS TRIBUTARIAS | G18: IRRF | I18: -0.02 | J18: =IF(I18="",".",J17+I18) -> 2.1104646e-14
A19: =A18+1 -> 14 | B19: 44735 | C19: =IF(B19="","",YEAR(B19)) -> 2022 | D19: Aplicaçao | F19: INVESTIMENTOS | G19: Aplicaçao | H19: B.B. | I19: 583210.91 | J19: =IF(I19="",".",J18+I19) -> 583210.91
A20: =A19+1 -> 15 | B20: 44742 | C20: =IF(B20="","",YEAR(B20)) -> 2022 | D20: Rendimento Bruto | E20: ENTRADAS | F20: JUROS | G20: Receitas Financeiras | I20: 1207.1 | J20: =IF(I20="",".",J19+I20) -> 584418.01
A21: =A20+1 -> 16 | B21: 44748 | C21: =IF(B21="","",YEAR(B21)) -> 2022 | D21: Resgate | F21: RESGATE | G21: Despesas Bancarias | H21: B.B. | I21: -66 | J21: =IF(I21="",".",J20+I21) -> 584352.01
A22: =A21+1 -> 17 | B22: 44771 | C22: =IF(B22="","",YEAR(B22)) -> 2022 | D22: Rendimento Bruto | E22: ENTRADAS | F22: JUROS | G22: Receitas Financeiras | I22: 5089.39 | J22: =IF(I22="",".",J21+I22) -> 589441.4 | K22: =(I22+I23+I24)/J20*12 -> 0.10449863
A23: =A22+1 -> 18 | B23: 44771 | C23: =IF(B23="","",YEAR(B23)) -> 2022 | D23: Imposto de Renda | E23: SAIDAS | F23: DESPESAS TRIBUTARIAS | G23: IRRF | I23: -0.02 | J23: =IF(I23="",".",J22+I23) -> 589441.38
A24: =A23+1 -> 19 | B24: 44771 | C24: =IF(B24="","",YEAR(B24)) -> 2022 | D24: I.O.F. | E24: SAIDAS | F24: DESPESAS TRIBUTARIAS | G24: IOF Bancario | I24: -0.13 | J24: =IF(I24="",".",J23+I24) -> 589441.25
A25: =A24+1 -> 20 | B25: 44778 | C25: =IF(B25="","",YEAR(B25)) -> 2022 | D25: Resgate | F25: RESGATE | G25: Despesas Bancarias | H25: B.B. | I25: -66 | J25: =IF(I25="",".",J24+I25) -> 589375.25
A26: =A25+1 -> 21 | B26: 44804 | C26: =IF(B26="","",YEAR(B26)) -> 2022 | D26: Rendimento Bruto | E26: ENTRADAS | F26: JUROS | G26: Receitas Financeiras | I26: 5849.96 | J26: =IF(I26="",".",J25+I26) -> 595225.21 | K26: =(I26+I27)/J24*12 -> 0.11909136
A27: =A26+1 -> 22 | B27: 44804 | C27: =IF(B27="","",YEAR(B27)) -> 2022 | D27: Imposto de Renda | E27: SAIDAS | F27: DESPESAS TRIBUTARIAS | G27: IRRF | I27: -0.18 | J27: =IF(I27="",".",J26+I27) -> 595225.03
A28: =A27+1 -> 23 | B28: 44809 | C28: =IF(B28="","",YEAR(B28)) -> 2022 | D28: Resgate | F28: RESGATE | G28: Despesas Bancarias | H28: B.B. | I28: -66 | J28: =IF(I28="",".",J27+I28) -> 595159.03
A29: =A28+1 -> 24 | B29: 44834 | C29: =IF(B29="","",YEAR(B29)) -> 2022 | D29: Rendimento Bruto | E29: ENTRADAS | F29: JUROS | G29: Receitas Financeiras | I29: 5442.88 | J29: =IF(I29="",".",J28+I29) -> 600601.91 | K29: =(I29+I30)/J27*12 -> 0.10972442
A30: =A29+1 -> 25 | B30: 44834 | C30: =IF(B30="","",YEAR(B30)) -> 2022 | D30: Imposto de Renda | E30: SAIDAS | F30: DESPESAS TRIBUTARIAS | G30: IRRF | I30: -0.32 | J30: =IF(I30="",".",J29+I30) -> 600601.59
A31: =A30+1 -> 26 | B31: 44839 | C31: =IF(B31="","",YEAR(B31)) -> 2022 | D31: Resgate | F31: RESGATE | G31: Despesas Bancarias | H31: B.B. | I31: -66 | J31: =IF(I31="",".",J30+I31) -> 600535.59
A32: =A31+1 -> 27 | B32: 44865 | C32: =IF(B32="","",YEAR(B32)) -> 2022 | D32: Rendimento Bruto | E32: ENTRADAS | F32: JUROS | G32: Receitas Financeiras | I32: 5248.75 | J32: =IF(I32="",".",J31+I32) -> 605784.34 | K32: =(I32+I33)/J30*12 -> 0.10486086
A33: =A32+1 -> 28 | B33: 44865 | C33: =IF(B33="","",YEAR(B33)) -> 2022 | D33: Imposto de Renda | E33: SAIDAS | F33: DESPESAS TRIBUTARIAS | G33: IRRF | I33: -0.45 | J33: =IF(I33="",".",J32+I33) -> 605783.89
A34: =A33+1 -> 29 | B34: 44872 | C34: =IF(B34="","",YEAR(B34)) -> 2022 | D34: Resgate | F34: RESGATE | G34: Despesas Bancarias | H34: B.B. | I34: -66 | J34: =IF(I34="",".",J33+I34) -> 605717.89
A35: =A34+1 -> 30 | B35: 44895 | C35: =IF(B35="","",YEAR(B35)) -> 2022 | D35: Rendimento Bruto | E35: ENTRADAS | F35: JUROS | G35: Receitas Financeiras | I35: 5202.77 | J35: =IF(I35="",".",J34+I35) -> 610920.66
A36: =A35+1 -> 31 | B36: 44895 | C36: =IF(B36="","",YEAR(B36)) -> 2022 | D36: Imposto de Renda | E36: SAIDAS | F36: DESPESAS TRIBUTARIAS | G36: IRRF | I36: -5607.32 | J36: =IF(I36="",".",J35+I36) -> 605313.34
A37: =A36+1 -> 32 | B37: 44900 | C37: =IF(B37="","",YEAR(B37)) -> 2022 | D37: Resgate | F37: RESGATE | G37: Despesas Bancarias | H37: B.B. | I37: -66 | J37: =IF(I37="",".",J36+I37) -> 605247.34
A38: =A37+1 -> 33 | B38: 44918 | C38: =IF(B38="","",YEAR(B38)) -> 2022 | D38: Resgate | F38: RESGATE | G38: Despesas Gerais | H38: B.B. | I38: -1050 | J38: =IF(I38="",".",J37+I38) -> 604197.34
A39: =A38+1 -> 34 | B39: 44925 | C39: =IF(B39="","",YEAR(B39)) -> 2022 | D39: Rendimento Bruto | E39: ENTRADAS | F39: JUROS | G39: Receitas Financeiras | I39: 5739.48 | J39: =IF(I39="",".",J38+I39) -> 609936.82 | K39: =(I39+I40)/J36*12 -> 0.11375008
A40: =A39+1 -> 35 | B40: 44925 | C40: =IF(B40="","",YEAR(B40)) -> 2022 | D40: Imposto de Renda | E40: SAIDAS | F40: DESPESAS TRIBUTARIAS | G40: IRRF | I40: -1.61 | J40: =IF(I40="",".",J39+I40) -> 609935.21
A41: =A40+1 -> 36 | B41: 44957 | C41: =IF(B41="","",YEAR(B41)) -> 2023 | D41: Rendimento Bruto | E41: ENTRADAS | F41: JUROS | G41: Receitas Financeiras | I41: 5802.12 | J41: =IF(I41="",".",J40+I41) -> 615737.33 | K41: =(I41)/J40*12 -> 0.11415219
A42: =A41+1 -> 37 | B42: 44958 | C42: =IF(B42="","",YEAR(B42)) -> 2023 | D42: Aplicaçao | F42: INVESTIMENTOS | G42: Aplicaçao | H42: B.B. | I42: 255040.77 | J42: =IF(I42="",".",J41+I42) -> 870778.1
A43: =A42+1 -> 38 | B43: 44963 | C43: =IF(B43="","",YEAR(B43)) -> 2023 | D43: Resgate | F43: RESGATE | G43: Despesas Bancarias | H43: B.B. | I43: -69 | J43: =IF(I43="",".",J42+I43) -> 870709.1
A44: =A43+1 -> 39 | B44: 44985 | C44: =IF(B44="","",YEAR(B44)) -> 2023 | D44: Rendimento Bruto | E44: ENTRADAS | F44: JUROS | G44: Receitas Financeiras | I44: 6703 | J44: =IF(I44="",".",J43+I44) -> 877412.1 | K44: =(I44+I45)/J43*12 -> 0.092376019
A45: =A44+1 -> 40 | B45: 44985 | C45: =IF(B45="","",YEAR(B45)) -> 2023 | D45: Imposto de Renda | E45: SAIDAS | F45: DESPESAS TRIBUTARIAS | G45: IRRF | I45: -0.28 | J45: =IF(I45="",".",J44+I45) -> 877411.82
A46: =A45+1 -> 41 | B46: 44991 | C46: =IF(B46="","",YEAR(B46)) -> 2023 | D46: Resgate | F46: RESGATE | G46: Despesas Bancarias | H46: B.B. | I46: -69 | J46: =IF(I46="",".",J45+I46) -> 877342.82
A47: =A46+1 -> 42 | B47: 45016 | C47: =IF(B47="","",YEAR(B47)) -> 2023 | D47: Rendimento Bruto | E47: ENTRADAS | F47: JUROS | G47: Receitas Financeiras | I47: 8678.45 | J47: =IF(I47="",".",J46+I47) -> 886021.27 | K47: =(I47+I48)/J46*12 -> 0.11869572
A48: =A47+1 -> 43 | B48: 45016 | C48: =IF(B48="","",YEAR(B48)) -> 2023 | D48: Imposto de Renda | E48: SAIDAS | F48: DESPESAS TRIBUTARIAS | G48: IRRF | I48: -0.38 | J48: =IF(I48="",".",J47+I48) -> 886020.89
A49: =A48+1 -> 44 | B49: 45022 | C49: =IF(B49="","",YEAR(B49)) -> 2023 | D49: Resgate | F49: RESGATE | G49: Despesas Bancarias | H49: B.B. | I49: -69 | J49: =IF(I49="",".",J48+I49) -> 885951.89
A50: =A49+1 -> 45 | B50: 45046 | C50: =IF(B50="","",YEAR(B50)) -> 2023 | D50: Rendimento Bruto | E50: ENTRADAS | F50: JUROS | G50: Receitas Financeiras | I50: 6760.43 | J50: =IF(I50="",".",J49+I50) -> 892712.32 | K50: =(I50+I51)/J49*12 -> 0.091561315
A51: =A50+1 -> 46 | B51: 45046 | C51: =IF(B51="","",YEAR(B51)) -> 2023 | D51: Imposto de Renda | E51: SAIDAS | F51: DESPESAS TRIBUTARIAS | G51: IRRF | I51: -0.52 | J51: =IF(I51="",".",J50+I51) -> 892711.8
A52: =A51+1 -> 47 | B52: 45051 | C52: =IF(B52="","",YEAR(B52)) -> 2023 | D52: Resgate | F52: RESGATE | G52: Despesas Bancarias | H52: B.B. | I52: -69 | J52: =IF(I52="",".",J51+I52) -> 892642.8
A53: =A52+1 -> 48 | B53: 45077 | C53: =IF(B53="","",YEAR(B53)) -> 2023 | D53: Resgate | F53: RESGATE | G53: Despesas Gerais | H53: B.B. | I53: -850 | J53: =IF(I53="",".",J52+I53) -> 891792.8
A54: =A53+1 -> 49 | B54: 45077 | C54: =IF(B54="","",YEAR(B54)) -> 2023 | D54: Rendimento Bruto | E54: ENTRADAS | F54: JUROS | G54: Receitas Financeiras | I54: 8579.24 | J54: =IF(I54="",".",J53+I54) -> 900372.04 | K54: =(I54+I55)/J53*12 -> 0.0017416153
A55: =A54+1 -> 50 | B55: 45077 | C55: =IF(B55="","",YEAR(B55)) -> 2023 | D55: Imposto de Renda | E55: SAIDAS | F55: DESPESAS TRIBUTARIAS | G55: IRRF | I55: -8449.81 | J55: =IF(I55="",".",J54+I55) -> 891922.23
A56: =A55+1 -> 51 | B56: 45082 | C56: =IF(B56="","",YEAR(B56)) -> 2023 | D56: Resgate | F56: RESGATE | G56: Despesas Bancarias | H56: B.B. | I56: -69 | J56: =IF(I56="",".",J55+I56) -> 891853.23
A57: =A56+1 -> 52 | B57: 45107 | C57: =IF(B57="","",YEAR(B57)) -> 2023 | D57: Rendimento Bruto | E57: ENTRADAS | F57: JUROS | G57: Receitas Financeiras | I57: 8186.54 | J57: =IF(I57="",".",J56+I57) -> 900039.77 | K57: =(I57+I58)/J56*12 -> 0.11015081
A58: =A57+1 -> 53 | B58: 45107 | C58: =IF(B58="","",YEAR(B58)) -> 2023 | D58: Imposto de Renda | E58: SAIDAS | F58: DESPESAS TRIBUTARIAS | G58: IRRF | I58: -0.01 | J58: =IF(I58="",".",J57+I58) -> 900039.76
A59: =A58+1 -> 54 | B59: 45112 | C59: =IF(B59="","",YEAR(B59)) -> 2023 | D59: Resgate | F59: RESGATE | G59: Despesas Bancarias | H59: B.B. | I59: -69 | J59: =IF(I59="",".",J58+I59) -> 899970.76
A60: =A59+1 -> 55 | B60: 45124 | C60: =IF(B60="","",YEAR(B60)) -> 2023 | D60: Resgate | F60: RESGATE | G60: Despesas Gerais | H60: B.B. | I60: -1200 | J60: =IF(I60="",".",J59+I60) -> 898770.76
A61: =A60+1 -> 56 | B61: 45138 | C61: =IF(B61="","",YEAR(B61)) -> 2023 | D61: Rendimento Bruto | E61: ENTRADAS | F61: JUROS | G61: Receitas Financeiras | I61: 8120.11 | J61: =IF(I61="",".",J60+I61) -> 906890.87 | K61: =(I61+I62)/J60*12 -> 0.10837041
A62: =A61+1 -> 57 | B62: 45138 | C62: =IF(B62="","",YEAR(B62)) -> 2023 | D62: Imposto de Renda | E62: SAIDAS | F62: DESPESAS TRIBUTARIAS | G62: IRRF | I62: -3.43 | J62: =IF(I62="",".",J61+I62) -> 906887.44
A63: =A62+1 -> 58 | B63: 45145 | C63: =IF(B63="","",YEAR(B63)) -> 2023 | D63: Resgate | F63: RESGATE | G63: Despesas Bancarias | H63: B.B. | I63: -69 | J63: =IF(I63="",".",J62+I63) -> 906818.44
A64: =A63+1 -> 59 | B64: 45169 | C64: =IF(B64="","",YEAR(B64)) -> 2023 | D64: Rendimento Bruto | E64: ENTRADAS | F64: JUROS | G64: Receitas Financeiras | I64: 8757.97 | J64: =IF(I64="",".",J63+I64) -> 915576.41 | K64: =(I64+I65)/J63*12 -> 0.11589134
A65: =A64+1 -> 60 | B65: 45169 | C65: =IF(B65="","",YEAR(B65)) -> 2023 | D65: Imposto de Renda | E65: SAIDAS | F65: DESPESAS TRIBUTARIAS | G65: IRRF | I65: -0.27 | J65: =IF(I65="",".",J64+I65) -> 915576.14
A66: =A65+1 -> 61 | B66: 45174 | C66: =IF(B66="","",YEAR(B66)) -> 2023 | D66: Resgate | F66: RESGATE | G66: Despesas Bancarias | H66: B.B. | I66: -69 | J66: =IF(I66="",".",J65+I66) -> 915507.14
A67: =A66+1 -> 62 | B67: 45199 | C67: =IF(B67="","",YEAR(B67)) -> 2023 | D67: Rendimento Bruto | E67: ENTRADAS | F67: JUROS | G67: Receitas Financeiras | I67: 7511.27 | J67: =IF(I67="",".",J66+I67) -> 923018.41 | K67: =(I67+I68)/J66*12 -> 0.098448779
A68: =A67+1 -> 63 | B68: 45199 | C68: =IF(B68="","",YEAR(B68)) -> 2023 | D68: Imposto de Renda | E68: SAIDAS | F68: DESPESAS TRIBUTARIAS | G68: IRRF | I68: -0.39 | J68: =IF(I68="",".",J67+I68) -> 923018.02
A69: =A68+1 -> 64 | B69: 45204 | C69: =IF(B69="","",YEAR(B69)) -> 2023 | D69: Resgate | F69: RESGATE | G69: Despesas Bancarias | H69: B.B. | I69: -69 | J69: =IF(I69="",".",J68+I69) -> 922949.02
A70: =A69+1 -> 65 | B70: 45230 | C70: =IF(B70="","",YEAR(B70)) -> 2023 | D70: Rendimento Bruto | E70: ENTRADAS | F70: JUROS | G70: Receitas Financeiras | I70: 7588.9 | J70: =IF(I70="",".",J69+I70) -> 930537.92 | K70: =(I70+I71)/J69*12 -> 0.098662741
A71: =A70+1 -> 66 | B71: 45230 | C71: =IF(B71="","",YEAR(B71)) -> 2023 | D71: Imposto de Renda | E71: SAIDAS | F71: DESPESAS TRIBUTARIAS | G71: IRRF | I71: -0.51 | J71: =IF(I71="",".",J70+I71) -> 930537.41
A72: =A71+1 -> 67 | B72: 45236 | C72: =IF(B72="","",YEAR(B72)) -> 2023 | D72: Resgate | F72: RESGATE | G72: Despesas Bancarias | H72: B.B. | I72: -69 | J72: =IF(I72="",".",J71+I72) -> 930468.41
A73: =A72+1 -> 68 | B73: 45260 | C73: =IF(B73="","",YEAR(B73)) -> 2023 | D73: Rendimento Bruto | E73: ENTRADAS | F73: JUROS | G73: Receitas Financeiras | I73: 7053.29 | J73: =IF(I73="",".",J72+I73) -> 937521.7 | K73: =(I73+I74)/J72*12 -> -0.030767471
A74: =A73+1 -> 69 | B74: 45260 | C74: =IF(B74="","",YEAR(B74)) -> 2023 | D74: Imposto de Renda | E74: SAIDAS | F74: DESPESAS TRIBUTARIAS | G74: IRRF | I74: -9438.97 | J74: =IF(I74="",".",J73+I74) -> 928082.73
A75: =A74+1 -> 70 | B75: 45265 | C75: =IF(B75="","",YEAR(B75)) -> 2023 | D75: Resgate | F75: RESGATE | G75: Despesas Bancarias | H75: B.B. | I75: -72 | J75: =IF(I75="",".",J74+I75) -> 928010.73
A76: =A75+1 -> 71 | B76: 45291 | C76: =IF(B76="","",YEAR(B76)) -> 2023 | D76: Rendimento Bruto | E76: ENTRADAS | F76: JUROS | G76: Receitas Financeiras | I76: 6908.87 | J76: =IF(I76="",".",J75+I76) -> 934919.6 | K76: =(I76+I77)/J74*12 -> 0.089330743 | L76: =(J42+J44+J47+J50+J54+J57+J61+J64+J61+J61+J67+J70+J73+J76)/12 -> 1057465.2 | M76: =('Resumo BB INV'!F30+'Resumo BB INV'!G30)/12 -> 6062.9675 | N76: =(M76/L76)*12 -> 0.068801896
A77: =A76+1 -> 72 | B77: 45291 | C77: =IF(B77="","",YEAR(B77)) -> 2023 | D77: Imposto de Renda | E77: SAIDAS | F77: DESPESAS TRIBUTARIAS | G77: IRRF | I77: -0.01 | J77: =IF(I77="",".",J76+I77) -> 934919.59 | L77: Giacenza media 2023 | M77: Imp. Medie mensili | N77: Rendimento netto
A78: =A77+1 -> 73 | B78: 45296 | C78: =IF(B78="","",YEAR(B78)) -> 2024 | D78: Resgate | F78: RESGATE | G78: Despesas Bancarias | H78: B.B. | I78: -72 | J78: =IF(I78="",".",J77+I78) -> 934847.59
A79: =A78+1 -> 74 | B79: 45322 | C79: =IF(B79="","",YEAR(B79)) -> 2024 | D79: Rendimento Bruto | E79: ENTRADAS | F79: JUROS | G79: Receitas Financeiras | I79: 7451.07 | J79: =IF(I79="",".",J78+I79) -> 942298.66 | K79: =(I79+I80)/J77*12 -> 0.09563539
A80: =A79+1 -> 75 | B80: 45322 | C80: =IF(B80="","",YEAR(B80)) -> 2024 | D80: Imposto de Renda | E80: SAIDAS | F80: DESPESAS TRIBUTARIAS | G80: IRRF | I80: -0.12 | J80: =IF(I80="",".",J79+I80) -> 942298.54
A81: =A80+1 -> 76 | B81: 45351 | C81: =IF(B81="","",YEAR(B81)) -> 2024 | D81: Rendimento Bruto | E81: ENTRADAS | F81: JUROS | G81: Receitas Financeiras | I81: 6186.6 | J81: =IF(I81="",".",J80+I81) -> 948485.14 | K81: =(I81+I82)/J79*12 -> 0.078785212
A82: =A81+1 -> 77 | B82: 45351 | C82: =IF(B82="","",YEAR(B82)) -> 2024 | D82: Imposto de Renda | E82: SAIDAS | F82: DESPESAS TRIBUTARIAS | G82: IRRF | I82: 0 | J82: =IF(I82="",".",J81+I82) -> 948485.14
A83: =A82+1 -> 78 | B83: 45382 | C83: =IF(B83="","",YEAR(B83)) -> 2024 | D83: Rendimento Bruto | E83: ENTRADAS | F83: JUROS | G83: Receitas Financeiras | I83: 6441.49 | J83: =IF(I83="",".",J82+I83) -> 954926.63 | K83: =(I83+I84)/J81*12 -> 0.081496142
A84: =A83+1 -> 79 | B84: 45382 | C84: =IF(B84="","",YEAR(B84)) -> 2024 | D84: Imposto de Renda | E84: SAIDAS | F84: DESPESAS TRIBUTARIAS | G84: IRRF | I84: 0 | J84: =IF(I84="",".",J83+I84) -> 954926.63
A85: =A84+1 -> 80 | B85: 45385 | C85: =IF(B85="","",YEAR(B85)) -> 2024 | D85: Resgate | F85: RESGATE | G85: Despesas Gerais | H85: B.B. | I85: -817.6 | J85: =IF(I85="",".",J84+I85) -> 954109.03
A86: =A85+1 -> 81 | B86: 45387 | C86: =IF(B86="","",YEAR(B86)) -> 2024 | D86: Resgate | F86: RESGATE | G86: Despesas Bancarias | H86: B.B. | I86: -72 | J86: =IF(I86="",".",J85+I86) -> 954037.03
A87: =A86+1 -> 82 | B87: 45412 | C87: =IF(B87="","",YEAR(B87)) -> 2024 | D87: Rendimento Bruto | E87: ENTRADAS | F87: JUROS | G87: Receitas Financeiras | I87: 6826.21 | J87: =IF(I87="",".",J86+I87) -> 960863.24 | K87: =(I87+I88)/J86*12 -> 0.08579516
A88: =A87+1 -> 83 | B88: 45412 | C88: =IF(B88="","",YEAR(B88)) -> 2024 | D88: Imposto de Renda | E88: SAIDAS | F88: DESPESAS TRIBUTARIAS | G88: IRRF | I88: -5.23 | J88: =IF(I88="",".",J87+I88) -> 960858.01
A89: =A88+1 -> 84 | B89: 45418 | C89: =IF(B89="","",YEAR(B89)) -> 2024 | D89: Resgate | F89: RESGATE | G89: Despesas Bancarias | H89: B.B. | I89: -72 | J89: =IF(I89="",".",J88+I89) -> 960786.01
A90: =A89+1 -> 85 | B90: 45441 | C90: =IF(B90="","",YEAR(B90)) -> 2024 | D90: Resgate | F90: RESGATE | G90: Despesas Bancarias | H90: B.B. | I90: -1049.08 | J90: =IF(I90="",".",J89+I90) -> 959736.93
A91: =A90+1 -> 86 | B91: 45443 | C91: =IF(B91="","",YEAR(B91)) -> 2024 | D91: Rendimento Bruto | E91: ENTRADAS | F91: JUROS | G91: Receitas Financeiras | I91: 6405.87 | J91: =IF(I91="",".",J90+I91) -> 966142.8 | K91: =(I91+I92)/J90*12 -> -0.019671641
A92: =A91+1 -> 87 | B92: 45443 | C92: =IF(B92="","",YEAR(B92)) -> 2024 | D92: Imposto de Renda | E92: SAIDAS | F92: DESPESAS TRIBUTARIAS | G92: IRRF | I92: -7979.17 | J92: =IF(I92="",".",J91+I92) -> 958163.63
A93: =A92+1 -> 88 | B93: 45448 | C93: =IF(B93="","",YEAR(B93)) -> 2024 | D93: Resgate | F93: RESGATE | G93: Despesas Bancarias | H93: B.B. | I93: -72 | J93: =IF(I93="",".",J92+I93) -> 958091.63
A94: =A93+1 -> 89 | B94: 45471 | C94: =IF(B94="","",YEAR(B94)) -> 2024 | D94: Rendimento Bruto | E94: ENTRADAS | F94: JUROS | G94: Receitas Financeiras | I94: 6084.94 | J94: =IF(I94="",".",J93+I94) -> 964176.57 | K94: =(I94+I95)/J93*12 -> 0.076213128
A95: =A94+1 -> 90 | B95: 45471 | C95: =IF(B95="","",YEAR(B95)) -> 2024 | D95: Imposto de Renda | E95: SAIDAS | F95: DESPESAS TRIBUTARIAS | G95: IRRF | I95: -0.01 | J95: =IF(I95="",".",J94+I95) -> 964176.56
A96: =A95+1 -> 91 | B96: 45478 | C96: =IF(B96="","",YEAR(B96)) -> 2024 | D96: Resgate | F96: RESGATE | G96: Despesas Bancarias | H96: B.B. | I96: -922 | J96: =IF(I96="",".",J95+I96) -> 963254.56
A97: =A96+1 -> 92 | B97: 45504 | C97: =IF(B97="","",YEAR(B97)) -> 2024 | D97: Rendimento Bruto | E97: ENTRADAS | F97: JUROS | G97: Receitas Financeiras | I97: 7046.15 | J97: =IF(I97="",".",J96+I97) -> 970300.71 | K97: =(I97+I98)/J96*12 -> 0.087760477
A98: =A97+1 -> 93 | B98: 45504 | C98: =IF(B98="","",YEAR(B98)) -> 2024 | D98: Imposto de Renda | E98: SAIDAS | F98: DESPESAS TRIBUTARIAS | G98: IRRF | I98: -1.51 | J98: =IF(I98="",".",J97+I98) -> 970299.2
A99: =A98+1 -> 94 | B99: 45509 | C99: =IF(B99="","",YEAR(B99)) -> 2024 | D99: Resgate | F99: RESGATE | G99: Despesas Bancarias | H99: B.B. | I99: -73.8 | J99: =IF(I99="",".",J98+I99) -> 970225.4
A100: =A99+1 -> 95 | B100: 45535 | C100: =IF(B100="","",YEAR(B100)) -> 2024 | D100: Rendimento Bruto | E100: ENTRADAS | F100: JUROS | G100: Receitas Financeiras | I100: 6811.3 | J100: =IF(I100="",".",J99+I100) -> 977036.7 | K100: =(I100+I101)/J99*12 -> 0.084241332
A101: =A100+1 -> 96 | B101: 45535 | C101: =IF(B101="","",YEAR(B101)) -> 2024 | D101: Imposto de Renda | E101: SAIDAS | F101: DESPESAS TRIBUTARIAS | G101: IRRF | I101: -0.21 | J101: =IF(I101="",".",J100+I101) -> 977036.49
...

Sheet Resumo BB INV
A3: Sum of Total | C3: Anno
A4: CATEGORIA | B4: TIPO | C4: 2021 | D4: 2022 | E4: 2023 | F4: 2024 | G4: 2025 | H4: 2026 | I4: Totale complessivo
A5: INVESTIMENTOS
B6: Aplicaçao | C6: 600000 | D6: 583210.91 | E6: 255040.77 | G6: 597295.96 | I6: 2035547.6
B7: Resgate | C7: -600000 | I7: -600000
A9: JUROS
B10: Receitas Financeiras | C10: 536.34 | D10: 33780.47 | E10: 90650.19 | F10: 80942.61 | G10: 135991.31 | H10: 141245.5 | I10: 483146.42
A12: DESPESAS TRIBUTARIAS
B13: IOF Bancario | C13: -445.05 | D13: -0.21 | I13: -445.26
B14: IRRF | C14: -20.5 | D14: -5609.93 | E14: -17894.58 | F14: -16073.35 | G14: -25469.15 | H14: -18588.53 | I14: -83656.04
A16: RESGATE
B17: Despesas Gerais | D17: -1050 | E17: -2050 | F17: -20209.99 | G17: -30788.37 | H17: -12024.75 | I17: -66123.11
B18: Cessione Credito | G18: -62000 | I18: -62000
B19: Despesas Bancarias | D19: -466.82 | E19: -762 | F19: -2812.08 | G19: -73.8 | I19: -4114.7
A21: Totale complessivo | C21: 70.79 | D21: 609864.42 | E21: 324984.38 | F21: 41847.19 | G21: 614955.95 | H21: 110632.22 | I21: 1702354.9
E26: RENDIMENTO FINANCIERO
E27: ANOS | F27: JUROS | G27: IMPOSTOS | H27: % IMP
E28: =C4 -> 2021 | F28: =C10 -> 536.34 | G28: =C13+C14 -> -465.55 | H28: =-G28/F28 -> 0.86801283
E29: =D4 -> 2022 | F29: =D10 -> 33780.47 | G29: =D13+D14 -> -5610.14 | H29: =-G29/F29 -> 0.16607643
E30: =E4 -> 2023 | F30: =E10 -> 90650.19 | G30: =E13+E14 -> -17894.58 | H30: =-G30/F30 -> 0.19740256
E31: =F4 -> 2024 | F31: =F10 -> 80942.61 | G31: =+F13+F14 -> -16073.35 | H31: =-G31/F31 -> 0.19857712
E32: =G4 -> 2025 | F32: =G10 -> 135991.31 | G32: =+G13+G14 -> -25469.15 | H32: =-G32/F32 -> 0.18728513
E33: =H4 -> 2026 | F33: =H10 -> 141245.5 | G33: =H13+H14 -> -18588.53 | H33: =-G33/F33 -> 0.13160441
E36: TOTAL | F36: =SUM(F28:F35) -> 483146.42 | G36: =SUM(G28:G35) -> -84101.3 | H36: =-G36/F36 -> 0.17407001

Sheet Consolidato
A1: Nr | B1: Date Comptable | C1: Anno | D1: Description | E1: E/U | F1: CATEGORIA | G1: TIPO | H1: Soggetto | I1: Total | J1: Solde
A2: 1 | B2: 44538 | C2: =IF(B2="","",YEAR(B2)) -> 2021 | D2: saldo anterior | I2: 0 | J2: =I2 -> 0
A3: =A2+1 -> 2 | B3: 44552 | C3: =IF(B3="","",YEAR(B3)) -> 2021 | D3: Transferencia recebida | E3: ENTRADAS | F3: LOCACAO | G3: Produtos | H3: JM EMPREENDIMENTOS IMOBILIARIO SCP LTDA | I3: 600000 | J3: =IF(I3="",".",J2+I3) -> 600000
A4: =A3+1 -> 3 | B4: 44553 | C4: =IF(B4="","",YEAR(B4)) -> 2021 | D4: Aplicaçao | F4: INVESTIMENTOS | G4: Aplicaçao | H4: B.B. | I4: -600000 | J4: =IF(I4="",".",J3+I4) -> 0
A5: =A4+1 -> 4 | B5: 44558 | C5: =IF(B5="","",YEAR(B5)) -> 2021 | D5: Resgate | F5: INVESTIMENTOS | G5: Resgate | H5: B.B. | I5: 600000 | J5: =IF(I5="",".",J4+I5) -> 600000
A6: =A5+1 -> 5 | B6: 44558 | C6: =IF(B6="","",YEAR(B6)) -> 2021 | D6: Pagamento terreno | E6: SAIDAS | F6: IMOBILIZACAO | G6: Terreno | H6: SOMBRA FLORESTA | I6: -600000 | J6: =IF(I6="",".",J5+I6) -> 0
A7: =A6+1 -> 6 | B7: 44566 | C7: =IF(B7="","",YEAR(B7)) -> 2022 | D7: Resgate | F7: INVESTIMENTOS | G7: Resgate | H7: B.B. | I7: 60 | J7: =IF(I7="",".",J6+I7) -> 60
A8: =A7+1 -> 7 | B8: 44566 | C8: =IF(B8="","",YEAR(B8)) -> 2022 | D8: Tarifa Pacote de Serviços | E8: SAIDAS | F8: DESPESAS FINANCEIRAS | G8: Despesas Bancarias | H8: B.B. | I8: -60 | J8: =IF(I8="",".",J7+I8) -> 0
A9: =A8+1 -> 8 | B9: 44599 | C9: =IF(B9="","",YEAR(B9)) -> 2022 | D9: Tarifa Pacote de Serviços | E9: SAIDAS | F9: DESPESAS FINANCEIRAS | G9: Despesas Bancarias | H9: B.B. | I9: -10.82 | J9: =IF(I9="",".",J8+I9) -> -10.82
A10: =A9+1 -> 9 | B10: 44599 | C10: =IF(B10="","",YEAR(B10)) -> 2022 | D10: Resgate | F10: INVESTIMENTOS | G10: Resgate | H10: B.B. | I10: 10.82 | J10: =IF(I10="",".",J9+I10) -> 0
A11: =A10+1 -> 10 | B11: 44607 | C11: =IF(B11="","",YEAR(B11)) -> 2022 | D11: Transferencia recebida | E11: ENTRADAS | F11: LOCACAO | G11: Produtos | H11: JM EMPREENDIMENTOS IMOB | I11: 183947.11 | J11: =IF(I11="",".",J10+I11) -> 183947.11
A12: =A11+1 -> 11 | B12: 44607 | C12: =IF(B12="","",YEAR(B12)) -> 2022 | D12: Tarifa Pacote de Serviços | E12: SAIDAS | F12: DESPESAS FINANCEIRAS | G12: Despesas Bancarias | H12: B.B. | I12: -55.18 | J12: =IF(I12="",".",J11+I12) -> 183891.93
A13: =A12+1 -> 12 | B13: 44608 | C13: =IF(B13="","",YEAR(B13)) -> 2022 | D13: Transferencia recebida | E13: ENTRADAS | F13: LOCACAO | G13: Produtos | H13: JM EMPREENDIMENTOS IMOB | I13: 200000 | J13: =IF(I13="",".",J12+I13) -> 383891.93
A14: =A13+1 -> 13 | B14: 44609 | C14: =IF(B14="","",YEAR(B14)) -> 2022 | D14: Transferencia recebida | E14: ENTRADAS | F14: LOCACAO | G14: Produtos | H14: JM EMPREENDIMENTOS IMOB | I14: 200000 | J14: =IF(I14="",".",J13+I14) -> 583891.93 | K14: -72.87 | L14: Taxa de localizaçao 2021
A15: =A14+1 -> 14 | B15: 44627 | C15: =IF(B15="","",YEAR(B15)) -> 2022 | D15: Tarifa Pacote de Serviços | E15: SAIDAS | F15: DESPESAS FINANCEIRAS | G15: Despesas Bancarias | H15: B.B. | I15: -66 | J15: =IF(I15="",".",J14+I15) -> 583825.93 | K15: -320.78 | L15: Taxa de localizaçao 2022
A16: =A15+1 -> 15 | B16: 44630 | C16: =IF(B16="","",YEAR(B16)) -> 2022 | D16: Impostos | E16: SAIDAS | F16: DESPESAS TRIBUTARIAS | G16: Taxa de Localizaçao 2021 | H16: PREF MUNICIPAL DE NATAL | I16: -72.87 | J16: =IF(I16="",".",J15+I16) -> 583753.06 | K16: =SUM(K14:K15) -> -393.65
A17: =A16+1 -> 16 | B17: 44631 | C17: =IF(B17="","",YEAR(B17)) -> 2022 | D17: Impostos | E17: SAIDAS | F17: DESPESAS TRIBUTARIAS | G17: Taxa de Localizaçao 2022 | H17: PREF MUNICIPAL DE NATAL | I17: -320.78 | J17: =IF(I17="",".",J16+I17) -> 583432.28 | K17: -23.37 | L17: Juros e multa
A18: =A17+1 -> 17 | B18: 44632 | C18: =IF(B18="","",YEAR(B18)) -> 2022 | D18: Impostos | E18: SAIDAS | F18: DESPESAS TRIBUTARIAS | G18: Juros e Multa | H18: PREF MUNICIPAL DE NATAL | I18: -23.37 | J18: =IF(I18="",".",J17+I18) -> 583408.91 | K18: =SUM(K16:K17) -> -417.02
A19: =A18+1 -> 18 | B19: 44656 | C19: =IF(B19="","",YEAR(B19)) -> 2022 | D19: Tarifa Pacote de Serviços | E19: SAIDAS | F19: DESPESAS FINANCEIRAS | G19: Despesas Bancarias | H19: B.B. | I19: -66 | J19: =IF(I19="",".",J18+I19) -> 583342.91
A20: =A19+1 -> 19 | B20: 44686 | C20: =IF(B20="","",YEAR(B20)) -> 2022 | D20: Tarifa Pacote de Serviços | E20: SAIDAS | F20: DESPESAS FINANCEIRAS | G20: Despesas Bancarias | H20: B.B. | I20: -66 | J20: =IF(I20="",".",J19+I20) -> 583276.91
A21: =A20+1 -> 20 | B21: 44718 | C21: =IF(B21="","",YEAR(B21)) -> 2022 | D21: Tarifa Pacote de Serviços | E21: SAIDAS | F21: DESPESAS FINANCEIRAS | G21: Despesas Bancarias | H21: B.B. | I21: -66 | J21: =IF(I21="",".",J20+I21) -> 583210.91
A22: =A21+1 -> 21 | B22: 44735 | C22: =IF(B22="","",YEAR(B22)) -> 2022 | D22: Aplicaçao | F22: INVESTIMENTOS | G22: Aplicaçao | H22: B.B. | I22: -583210.91 | J22: =IF(I22="",".",J21+I22) -> -1.1641532e-10
A23: =A22+1 -> 22 | B23: 44748 | C23: =IF(B23="","",YEAR(B23)) -> 2022 | D23: Tarifa Pacote de Serviços | E23: SAIDAS | F23: DESPESAS FINANCEIRAS | G23: Despesas Bancarias | H23: B.B. | I23: -66 | J23: =IF(I23="",".",J22+I23) -> -66
A24: =A23+1 -> 23 | B24: 44748 | C24: =IF(B24="","",YEAR(B24)) -> 2022 | D24: Resgate | F24: INVESTIMENTOS | G24: Resgate | H24: B.B. | I24: 66 | J24: =IF(I24="",".",J23+I24) -> -1.1641532e-10
A25: =A24+1 -> 24 | B25: 44778 | C25: =IF(B25="","",YEAR(B25)) -> 2022 | D25: Tarifa Pacote de Serviços | E25: SAIDAS | F25: DESPESAS FINANCEIRAS | G25: Despesas Bancarias | H25: B.B. | I25: -66 | J25: =IF(I25="",".",J24+I25) -> -66
A26: =A25+1 -> 25 | B26: 44778 | C26: =IF(B26="","",YEAR(B26)) -> 2022 | D26: Resgate | F26: INVESTIMENTOS | G26: Resgate | H26: B.B. | I26: 66 | J26: =IF(I26="",".",J25+I26) -> -1.1641532e-10
A27: =A26+1 -> 26 | B27: 44809 | C27: =IF(B27="","",YEAR(B27)) -> 2022 | D27: Tarifa Pacote de Serviços | E27: SAIDAS | F27: DESPESAS FINANCEIRAS | G27: Despesas Bancarias | H27: B.B. | I27: -66 | J27: =IF(I27="",".",J26+I27) -> -66
A28: =A27+1 -> 27 | B28: 44809 | C28: =IF(B28="","",YEAR(B28)) -> 2022 | D28: Resgate | F28: INVESTIMENTOS | G28: Resgate | H28: B.B. | I28: 66 | J28: =IF(I28="",".",J27+I28) -> -1.1641532e-10
A29: =A28+1 -> 28 | B29: 44839 | C29: =IF(B29="","",YEAR(B29)) -> 2022 | D29: Tarifa Pacote de Serviços | E29: SAIDAS | F29: DESPESAS FINANCEIRAS | G29: Despesas Bancarias | H29: B.B. | I29: -66 | J29: =IF(I29="",".",J28+I29) -> -66
A30: =A29+1 -> 29 | B30: 44839 | C30: =IF(B30="","",YEAR(B30)) -> 2022 | D30: Resgate | F30: INVESTIMENTOS | G30: Resgate | H30: B.B. | I30: 66 | J30: =IF(I30="",".",J29+I30) -> -1.1641532e-10
A31: =A30+1 -> 30 | B31: 44872 | C31: =IF(B31="","",YEAR(B31)) -> 2022 | D31: Tarifa Pacote de Serviços | E31: SAIDAS | F31: DESPESAS FINANCEIRAS | G31: Despesas Bancarias | H31: B.B. | I31: -66 | J31: =IF(I31="",".",J30+I31) -> -66
A32: =A31+1 -> 31 | B32: 44872 | C32: =IF(B32="","",YEAR(B32)) -> 2022 | D32: Resgate | F32: INVESTIMENTOS | G32: Resgate | H32: B.B. | I32: 66 | J32: =IF(I32="",".",J31+I32) -> -1.1641532e-10
A33: =A32+1 -> 32 | B33: 44900 | C33: =IF(B33="","",YEAR(B33)) -> 2022 | D33: Tarifa Pacote de Serviços | E33: SAIDAS | F33: DESPESAS FINANCEIRAS | G33: Despesas Bancarias | H33: B.B. | I33: -66 | J33: =IF(I33="",".",J32+I33) -> -66
A34: =A33+1 -> 33 | B34: 44900 | C34: =IF(B34="","",YEAR(B34)) -> 2022 | D34: Resgate | F34: INVESTIMENTOS | G34: Resgate | H34: B.B. | I34: 66 | J34: =IF(I34="",".",J33+I34) -> -1.1641532e-10
A35: =A34+1 -> 34 | B35: 44918 | C35: =IF(B35="","",YEAR(B35)) -> 2022 | D35: 50% Traduzione giurata dello Statuto | E35: SAIDAS | F35: DESPESAS GERAIS | G35: Varias | H35: Antonio Francisco Alves Ro | I35: -1050 | J35: =IF(I35="",".",J34+I35) -> -1050
A36: =A35+1 -> 35 | B36: 44918 | C36: =IF(B36="","",YEAR(B36)) -> 2022 | D36: Resgate | F36: INVESTIMENTOS | G36: Resgate | H36: B.B. | I36: 1050 | J36: =IF(I36="",".",J35+I36) -> -1.1641532e-10
A37: =A36+1 -> 36 | B37: 44924 | C37: =IF(B37="","",YEAR(B37)) -> 2022 | D37: Transferencia recebida | E37: ENTRADAS | F37: LOCACAO | G37: Produtos | H37: JM EMPREENDIMENTOS IMOBILIARIO SCP LTDA | I37: 255109.77 | J37: =IF(I37="",".",J36+I37) -> 255109.77
A38: =A37+1 -> 37 | B38: 44931 | C38: =IF(B38="","",YEAR(B38)) -> 2023 | D38: Tarifa Pacote de Serviços | E38: SAIDAS | F38: DESPESAS FINANCEIRAS | G38: Despesas Bancarias | H38: B.B. | I38: -69 | J38: =IF(I38="",".",J37+I38) -> 255040.77
A39: =A38+1 -> 38 | B39: 44958 | C39: =IF(B39="","",YEAR(B39)) -> 2023 | D39: Aplicaçao | F39: INVESTIMENTOS | G39: Aplicaçao | H39: B.B. | I39: -255040.77 | J39: =IF(I39="",".",J38+I39) -> -1.1641532e-10
A40: =A39+1 -> 39 | B40: 44963 | C40: =IF(B40="","",YEAR(B40)) -> 2023 | D40: Tarifa Pacote de Serviços | E40: SAIDAS | F40: DESPESAS FINANCEIRAS | G40: Despesas Bancarias | H40: B.B. | I40: -69 | J40: =IF(I40="",".",J39+I40) -> -69
A41: =A40+1 -> 40 | B41: 44963 | C41: =IF(B41="","",YEAR(B41)) -> 2023 | D41: Resgate | F41: INVESTIMENTOS | G41: Resgate | H41: B.B. | I41: 69 | J41: =IF(I41="",".",J40+I41) -> -1.1641532e-10
A42: =A41+1 -> 41 | B42: 44991 | C42: =IF(B42="","",YEAR(B42)) -> 2023 | D42: Tarifa Pacote de Serviços | E42: SAIDAS | F42: DESPESAS FINANCEIRAS | G42: Despesas Bancarias | H42: B.B. | I42: -69 | J42: =IF(I42="",".",J41+I42) -> -69
A43: =A42+1 -> 42 | B43: 44991 | C43: =IF(B43="","",YEAR(B43)) -> 2023 | D43: Resgate | F43: INVESTIMENTOS | G43: Resgate | H43: B.B. | I43: 69 | J43: =IF(I43="",".",J42+I43) -> -1.1641532e-10
A44: =A43+1 -> 43 | B44: 45022 | C44: =IF(B44="","",YEAR(B44)) -> 2023 | D44: Tarifa Pacote de Serviços | E44: SAIDAS | F44: DESPESAS FINANCEIRAS | G44: Despesas Bancarias | H44: B.B. | I44: -69 | J44: =IF(I44="",".",J43+I44) -> -69
A45: =A44+1 -> 44 | B45: 45022 | C45: =IF(B45="","",YEAR(B45)) -> 2023 | D45: Resgate | F45: INVESTIMENTOS | G45: Resgate | H45: B.B. | I45: 69 | J45: =IF(I45="",".",J44+I45) -> -1.1641532e-10
A46: =A45+1 -> 45 | B46: 45051 | C46: =IF(B46="","",YEAR(B46)) -> 2023 | D46: Tarifa Pacote de Serviços | E46: SAIDAS | F46: DESPESAS FINANCEIRAS | G46: Despesas Bancarias | H46: B.B. | I46: -69 | J46: =IF(I46="",".",J45+I46) -> -69
A47: =A46+1 -> 46 | B47: 45051 | C47: =IF(B47="","",YEAR(B47)) -> 2023 | D47: Resgate | F47: INVESTIMENTOS | G47: Resgate | H47: B.B. | I47: 69 | J47: =IF(I47="",".",J46+I47) -> -1.1641532e-10
A48: =A47+1 -> 47 | B48: 45077 | C48: =IF(B48="","",YEAR(B48)) -> 2023 | D48: Domiciliazione societaria | E48: SAIDAS | F48: DESPESAS GERAIS | G48: Varias | H48: ONE Empreendimentos Serviços | I48: -850 | J48: =IF(I48="",".",J47+I48) -> -850
A49: =A48+1 -> 48 | B49: 45077 | C49: =IF(B49="","",YEAR(B49)) -> 2023 | D49: Resgate | F49: INVESTIMENTOS | G49: Resgate | H49: B.B. | I49: 850 | J49: =IF(I49="",".",J48+I49) -> -1.1641532e-10
A50: =A49+1 -> 49 | B50: 45082 | C50: =IF(B50="","",YEAR(B50)) -> 2023 | D50: Tarifa Pacote de Serviços | E50: SAIDAS | F50: DESPESAS FINANCEIRAS | G50: Despesas Bancarias | H50: B.B. | I50: -69 | J50: =IF(I50="",".",J49+I50) -> -69
A51: =A50+1 -> 50 | B51: 45082 | C51: =IF(B51="","",YEAR(B51)) -> 2023 | D51: Resgate | F51: INVESTIMENTOS | G51: Resgate | H51: B.B. | I51: 69 | J51: =IF(I51="",".",J50+I51) -> -1.1641532e-10
A52: =A51+1 -> 51 | B52: 45112 | C52: =IF(B52="","",YEAR(B52)) -> 2023 | D52: Tarifa Pacote de Serviços | E52: SAIDAS | F52: DESPESAS FINANCEIRAS | G52: Despesas Bancarias | H52: B.B. | I52: -69 | J52: =IF(I52="",".",J51+I52) -> -69
A53: =A52+1 -> 52 | B53: 45112 | C53: =IF(B53="","",YEAR(B53)) -> 2023 | D53: Resgate | F53: INVESTIMENTOS | G53: Resgate | H53: B.B. | I53: 69 | J53: =IF(I53="",".",J52+I53) -> -1.1641532e-10
A54: =A53+1 -> 53 | B54: 45124 | C54: =IF(B54="","",YEAR(B54)) -> 2023 | D54: Cambiamento indirizzo societario | E54: SAIDAS | F54: DESPESAS GERAIS | G54: Varias | H54: Igor R.R. Franca Sociedade - Junta Comercial | I54: -1200 | J54: =IF(I54="",".",J53+I54) -> -1200
A55: =A54+1 -> 54 | B55: 45124 | C55: =IF(B55="","",YEAR(B55)) -> 2023 | D55: Resgate | F55: INVESTIMENTOS | G55: Resgate | H55: B.B. | I55: 1200 | J55: =IF(I55="",".",J54+I55) -> -1.1641532e-10
A56: =A55+1 -> 55 | B56: 45145 | C56: =IF(B56="","",YEAR(B56)) -> 2023 | D56: Tarifa Pacote de Serviços | E56: SAIDAS | F56: DESPESAS FINANCEIRAS | G56: Despesas Bancarias | H56: B.B. | I56: -69 | J56: =IF(I56="",".",J55+I56) -> -69
A57: =A56+1 -> 56 | B57: 45145 | C57: =IF(B57="","",YEAR(B57)) -> 2023 | D57: Resgate | F57: INVESTIMENTOS | G57: Resgate | H57: B.B. | I57: 69 | J57: =IF(I57="",".",J56+I57) -> -1.1641532e-10
A58: =A57+1 -> 57 | B58: 45174 | C58: =IF(B58="","",YEAR(B58)) -> 2023 | D58: Tarifa Pacote de Serviços | E58: SAIDAS | F58: DESPESAS FINANCEIRAS | G58: Despesas Bancarias | H58: B.B. | I58: -69 | J58: =IF(I58="",".",J57+I58) -> -69
A59: =A58+1 -> 58 | B59: 45174 | C59: =IF(B59="","",YEAR(B59)) -> 2023 | D59: Resgate | F59: INVESTIMENTOS | G59: Resgate | H59: B.B. | I59: 69 | J59: =IF(I59="",".",J58+I59) -> -1.1641532e-10
A60: =A59+1 -> 59 | B60: 45204 | C60: =IF(B60="","",YEAR(B60)) -> 2023 | D60: Tarifa Pacote de Serviços | E60: SAIDAS | F60: DESPESAS FINANCEIRAS | G60: Despesas Bancarias | H60: B.B. | I60: -69 | J60: =IF(I60="",".",J59+I60) -> -69
A61: =A60+1 -> 60 | B61: 45204 | C61: =IF(B61="","",YEAR(B61)) -> 2023 | D61: Resgate | F61: INVESTIMENTOS | G61: Resgate | H61: B.B. | I61: 69 | J61: =IF(I61="",".",J60+I61) -> -1.1641532e-10
A62: =A61+1 -> 61 | B62: 45236 | C62: =IF(B62="","",YEAR(B62)) -> 2023 | D62: Tarifa Pacote de Serviços | E62: SAIDAS | F62: DESPESAS FINANCEIRAS | G62: Despesas Bancarias | H62: B.B. | I62: -69 | J62: =IF(I62="",".",J61+I62) -> -69
A63: =A62+1 -> 62 | B63: 45236 | C63: =IF(B63="","",YEAR(B63)) -> 2023 | D63: Resgate | F63: INVESTIMENTOS | G63: Resgate | H63: B.B. | I63: 69 | J63: =IF(I63="",".",J62+I63) -> -1.1641532e-10
A64: =A63+1 -> 63 | B64: 45265 | C64: =IF(B64="","",YEAR(B64)) -> 2023 | D64: Tarifa Pacote de Serviços | E64: SAIDAS | F64: DESPESAS FINANCEIRAS | G64: Despesas Bancarias | H64: B.B. | I64: -72 | J64: =IF(I64="",".",J63+I64) -> -72
A65: =A64+1 -> 64 | B65: 45265 | C65: =IF(B65="","",YEAR(B65)) -> 2023 | D65: Resgate | F65: INVESTIMENTOS | G65: Resgate | H65: B.B. | I65: 72 | J65: =IF(I65="",".",J64+I65) -> -1.1641532e-10
A66: =A65+1 -> 65 | B66: 45296 | C66: =IF(B66="","",YEAR(B66)) -> 2024 | D66: Tarifa Pacote de Serviços | E66: SAIDAS | F66: DESPESAS FINANCEIRAS | G66: Despesas Bancarias | H66: B.B. | I66: -72 | J66: =IF(I66="",".",J65+I66) -> -72
A67: =A66+1 -> 66 | B67: 45296 | C67: =IF(B67="","",YEAR(B67)) -> 2024 | D67: Resgate | F67: INVESTIMENTOS | G67: Resgate | H67: B.B. | I67: 72 | J67: =IF(I67="",".",J66+I67) -> -1.1641532e-10
A68: =A67+1 -> 67 | B68: 45385 | C68: =IF(B68="","",YEAR(B68)) -> 2024 | D68: Impostos e Taxas | E68: SAIDAS | F68: DESPESAS TRIBUTARIAS | G68: Taxa de Localizaçao 2023 | H68: Prefeitura NATAL | I68: -408.82 | J68: =IF(I68="",".",J67+I68) -> -408.82
A69: =A68+1 -> 68 | B69: 45385 | C69: =IF(B69="","",YEAR(B69)) -> 2024 | D69: Taxa de Localizaçao | E69: SAIDAS | F69: DESPESAS TRIBUTARIAS | G69: Taxa de Localizaçao 2024 | H69: Prefeitura NATAL | I69: -408.78 | J69: =IF(I69="",".",J68+I69) -> -817.6
A70: =A69+1 -> 69 | B70: 45385 | C70: =IF(B70="","",YEAR(B70)) -> 2024 | D70: Resgate | F70: INVESTIMENTOS | G70: Resgate | H70: B.B. | I70: 817.6 | J70: =IF(I70="",".",J69+I70) -> -1.1630163e-10
A71: =A70+1 -> 70 | B71: 45387 | C71: =IF(B71="","",YEAR(B71)) -> 2024 | D71: Tarifa Pacote de Serviços | E71: SAIDAS | F71: DESPESAS FINANCEIRAS | G71: Despesas Bancarias | H71: B.B. | I71: -72 | J71: =IF(I71="",".",J70+I71) -> -72
A72: =A71+1 -> 71 | B72: 45387 | C72: =IF(B72="","",YEAR(B72)) -> 2024 | D72: Resgate | F72: INVESTIMENTOS | G72: Resgate | H72: B.B. | I72: 72 | J72: =IF(I72="",".",J71+I72) -> -1.1630163e-10
A73: =A72+1 -> 72 | B73: 45418 | C73: =IF(B73="","",YEAR(B73)) -> 2024 | D73: Tarifa Pacote de Serviços | E73: SAIDAS | F73: DESPESAS FINANCEIRAS | G73: Despesas Bancarias | H73: B.B. | I73: -72 | J73: =IF(I73="",".",J72+I73) -> -72
A74: =A73+1 -> 73 | B74: 45418 | C74: =IF(B74="","",YEAR(B74)) -> 2024 | D74: Resgate | F74: INVESTIMENTOS | G74: Resgate | H74: B.B. | I74: 72 | J74: =IF(I74="",".",J73+I74) -> -1.1630163e-10
A75: =A74+1 -> 74 | B75: 45441 | C75: =IF(B75="","",YEAR(B75)) -> 2024 | D75: Spese Cartorio | E75: SAIDAS | F75: DESPESAS GERAIS | G75: Varias | H75: Natal - Cartorio 2 Oficio Nota | I75: -1049.08 | J75: =IF(I75="",".",J74+I75) -> -1049.08
A76: =A75+1 -> 75 | B76: 45441 | C76: =IF(B76="","",YEAR(B76)) -> 2024 | D76: Resgate | F76: INVESTIMENTOS | G76: Resgate | H76: B.B. | I76: 1049.08 | J76: =IF(I76="",".",J75+I76) -> -1.1641532e-10
A77: =A76+1 -> 76 | B77: 45448 | C77: =IF(B77="","",YEAR(B77)) -> 2024 | D77: Tarifa Pacote de Serviços | E77: SAIDAS | F77: DESPESAS FINANCEIRAS | G77: Despesas Bancarias | H77: B.B. | I77: -72 | J77: =IF(I77="",".",J76+I77) -> -72
A78: =A77+1 -> 77 | B78: 45448 | C78: =IF(B78="","",YEAR(B78)) -> 2024 | D78: Resgate | F78: INVESTIMENTOS | G78: Resgate | H78: B.B. | I78: 72 | J78: =IF(I78="",".",J77+I78) -> -1.1641532e-10
A79: =A78+1 -> 78 | B79: 45478 | C79: =IF(B79="","",YEAR(B79)) -> 2024 | D79: Domiciliazione societaria | E79: SAIDAS | F79: DESPESAS GERAIS | G79: Varias | H79: ONE Empreendimentos Serviços | I79: -850 | J79: =IF(I79="",".",J78+I79) -> -850
A80: =A79+1 -> 79 | B80: 45478 | C80: =IF(B80="","",YEAR(B80)) -> 2024 | D80: Tarifa Pacote de Serviços | E80: SAIDAS | F80: DESPESAS FINANCEIRAS | G80: Despesas Bancarias | H80: B.B. | I80: -72 | J80: =IF(I80="",".",J79+I80) -> -922
A81: =A80+1 -> 80 | B81: 45478 | C81: =IF(B81="","",YEAR(B81)) -> 2024 | D81: Resgate | F81: INVESTIMENTOS | G81: Resgate | H81: B.B. | I81: 922 | J81: =IF(I81="",".",J80+I81) -> -1.1641532e-10
A82: =A81+1 -> 81 | B82: 45509 | C82: =IF(B82="","",YEAR(B82)) -> 2024 | D82: Tarifa Pacote de Serviços | E82: SAIDAS | F82: DESPESAS FINANCEIRAS | G82: Despesas Bancarias | H82: B.B. | I82: -73.8 | J82: =IF(I82="",".",J81+I82) -> -73.8
A83: =A82+1 -> 82 | B83: 45509 | C83: =IF(B83="","",YEAR(B83)) -> 2024 | D83: Resgate | F83: INVESTIMENTOS | G83: Resgate | H83: B.B. | I83: 73.8 | J83: =IF(I83="",".",J82+I83) -> -1.1641532e-10
A84: =A83+1 -> 83 | B84: 45540 | C84: =IF(B84="","",YEAR(B84)) -> 2024 | D84: Tarifa Pacote de Serviços | E84: SAIDAS | F84: DESPESAS FINANCEIRAS | G84: Despesas Bancarias | H84: B.B. | I84: -73.8 | J84: =IF(I84="",".",J83+I84) -> -73.8
A85: =A84+1 -> 84 | B85: 45540 | C85: =IF(B85="","",YEAR(B85)) -> 2024 | D85: Resgate | F85: INVESTIMENTOS | G85: Resgate | H85: B.B. | I85: 73.8 | J85: =IF(I85="",".",J84+I85) -> -1.1641532e-10
A86: =A85+1 -> 85 | B86: 45572 | C86: =IF(B86="","",YEAR(B86)) -> 2024 | D86: Tarifa Pacote de Serviços | E86: SAIDAS | F86: DESPESAS FINANCEIRAS | G86: Despesas Bancarias | H86: B.B. | I86: -73.8 | J86: =IF(I86="",".",J85+I86) -> -73.8
A87: =A86+1 -> 86 | B87: 45572 | C87: =IF(B87="","",YEAR(B87)) -> 2024 | D87: Resgate | F87: INVESTIMENTOS | G87: Resgate | H87: B.B. | I87: 73.8 | J87: =IF(I87="",".",J86+I87) -> -1.1641532e-10
A88: =A87+1 -> 87 | B88: 45596 | C88: =IF(B88="","",YEAR(B88)) -> 2024 | D88: Spese Cartorio | E88: SAIDAS | F88: DESPESAS GERAIS | G88: Varias | H88: Essencial Gestao Empresarial LTDA | I88: -184 | J88: =IF(I88="",".",J87+I88) -> -184
A89: =A88+1 -> 88 | B89: 45596 | C89: =IF(B89="","",YEAR(B89)) -> 2024 | D89: Resgate | F89: INVESTIMENTOS | G89: Resgate | H89: B.B. | I89: 184 | J89: =IF(I89="",".",J88+I89) -> -1.1641532e-10
A90: =A89+1 -> 89 | B90: 45601 | C90: =IF(B90="","",YEAR(B90)) -> 2024 | D90: Tarifa Pacote de Serviços | E90: SAIDAS | F90: DESPESAS FINANCEIRAS | G90: Despesas Bancarias | H90: B.B. | I90: -73.8 | J90: =IF(I90="",".",J89+I90) -> -73.8
A91: =A90+1 -> 90 | B91: 45601 | C91: =IF(B91="","",YEAR(B91)) -> 2024 | D91: Resgate | F91: INVESTIMENTOS | G91: Resgate | H91: B.B. | I91: 73.8 | J91: =IF(I91="",".",J90+I91) -> -1.1641532e-10
A92: =A91+1 -> 91 | B92: 45603 | C92: =IF(B92="","",YEAR(B92)) -> 2024 | D92: Compra de Madeira | E92: SAIDAS | F92: DESPESAS GERAIS | G92: Varias | H92: Mac Madeira Ltd | I92: -421.6 | J92: =IF(I92="",".",J91+I92) -> -421.6
A93: =A92+1 -> 92 | B93: 45603 | C93: =IF(B93="","",YEAR(B93)) -> 2024 | D93: Resgate | F93: INVESTIMENTOS | G93: Resgate | H93: B.B. | I93: 421.6 | J93: =IF(I93="",".",J92+I93) -> -1.1641532e-10
A94: =A93+1 -> 93 | B94: 45625 | C94: =IF(B94="","",YEAR(B94)) -> 2024 | D94: Financeiro | E94: SAIDAS | F94: DESPESAS GERAIS | G94: Varias | H94: Elenice Aurea Solares | I94: -300 | J94: =IF(I94="",".",J93+I94) -> -300
A95: =A94+1 -> 94 | B95: 45625 | C95: =IF(B95="","",YEAR(B95)) -> 2024 | D95: Honorario Contabeis | E95: SAIDAS | F95: DESPESAS GERAIS | G95: Varias | H95: Elenice Aurea Solares | I95: -353 | J95: =IF(I95="",".",J94+I95) -> -653
A96: =A95+1 -> 95 | B96: 45625 | C96: =IF(B96="","",YEAR(B96)) -> 2024 | D96: Resgate | F96: INVESTIMENTOS | G96: Resgate | H96: B.B. | I96: 653 | J96: =IF(I96="",".",J95+I96) -> -1.1641532e-10
A97: =A96+1 -> 96 | B97: 45631 | C97: =IF(B97="","",YEAR(B97)) -> 2024 | D97: Tarifa Pacote de Serviços | E97: SAIDAS | F97: DESPESAS FINANCEIRAS | G97: Despesas Bancarias | H97: B.B. | I97: -73.8 | J97: =IF(I97="",".",J96+I97) -> -73.8
A98: =A97+1 -> 97 | B98: 45631 | C98: =IF(B98="","",YEAR(B98)) -> 2024 | D98: Resgate | F98: INVESTIMENTOS | G98: Resgate | H98: B.B. | I98: 73.8 | J98: =IF(I98="",".",J97+I98) -> -1.1641532e-10
A99: =A98+1 -> 98 | B99: 45632 | C99: =IF(B99="","",YEAR(B99)) -> 2024 | D99: Honorario Contabeis | E99: SAIDAS | F99: DESPESAS GERAIS | G99: Varias | H99: Elenice Aurea Soares | I99: -653 | J99: =IF(I99="",".",J98+I99) -> -653
A100: =A99+1 -> 99 | B100: 45632 | C100: =IF(B100="","",YEAR(B100)) -> 2024 | D100: Resgate | F100: INVESTIMENTOS | G100: Resgate | H100: B.B. | I100: 653 | J100: =IF(I100="",".",J99+I100) -> -1.1641532e-10
...

Sheet Pivot cons
A3: Sum of Total | B3: Etichette di colonna
A4: Etichette di riga | B4: 2021 | C4: 2022 | D4: 2023 | E4: 2024 | F4: 2025 | G4: 2026 | H4: Totale complessivo
A5: ENTRADAS
A6: LOCACAO
A7: Produtos | B7: 600000 | C7: 839056.88 | F7: 617509.26 | G7: 43156.04 | H7: 2099722.2
A8: LOCACAO Totale | B8: 600000 | C8: 839056.88 | F8: 617509.26 | G8: 43156.04 | H8: 2099722.2
A9: JUROS
A10: Receitas Financeiras | B10: 536.34 | C10: 33780.47 | D10: 90650.19 | E10: 80942.61 | F10: 135991.31 | G10: 141245.5 | H10: 483146.42
A11: JUROS Totale | B11: 536.34 | C11: 33780.47 | D11: 90650.19 | E11: 80942.61 | F11: 135991.31 | G11: 141245.5 | H11: 483146.42
A12: ENTRADAS Totale | B12: 600536.34 | C12: 872837.35 | D12: 90650.19 | E12: 80942.61 | F12: 753500.57 | G12: 184401.54 | H12: 2582868.6
A13: SAIDAS
A14: IMOBILIZACAO
A15: Terreno | B15: -600000 | H15: -600000
A16: IMOBILIZACAO Totale | B16: -600000 | H16: -600000
A17: DESPESAS FINANCEIRAS
A18: Despesas Bancarias | C18: -786 | D18: -831 | E18: -729 | F18: -925.6 | G18: -791.1 | H18: -4062.7
A19: DESPESAS FINANCEIRAS Totale | C19: -786 | D19: -831 | E19: -729 | F19: -925.6 | G19: -791.1 | H19: -4062.7
A20: DESPESAS TRIBUTARIAS
A21: Juros e Multa | C21: -23.37 | H21: -23.37
A22: Taxa de Localizaçao 2021 | C22: -72.87 | H22: -72.87
A23: Taxa de Localizaçao 2022 | C23: -320.78 | H23: -320.78
A24: Taxa de Localizaçao 2023 | E24: -408.82 | H24: -408.82
A25: Taxa de Localizaçao 2024 | E25: -408.78 | H25: -408.78
A26: Taxa de Localizaçao 2025 | F26: -378.61 | H26: -378.61
A27: Taxa de Localizaçao 2026 | G27: -398.75 | H27: -398.75
A28: IOF Bancario | B28: -445.05 | C28: -0.21 | H28: -445.26
A29: IRRF | B29: -20.5 | C29: -5609.93 | D29: -17894.58 | E29: -16073.35 | F29: -25469.15 | G29: -18588.53 | H29: -83656.04
A30: DESPESAS TRIBUTARIAS Totale | B30: -465.55 | C30: -6027.16 | D30: -17894.58 | E30: -16890.95 | F30: -25847.76 | G30: -18987.28 | H30: -86113.28
A31: DESPESAS GERAIS
A32: Varias | C32: -1050 | D32: -2050 | E32: -21475.47 | F32: -17822.03 | G32: -935.39 | H32: -43332.89
A33: Gestao Empresarial | F33: -15610 | G33: -21208.31 | H33: -36818.31
A34: Moveis Casa H | F34: -7482.84 | H34: -7482.84
A35: DESPESAS GERAIS Totale | C35: -1050 | D35: -2050 | E35: -21475.47 | F35: -40914.87 | G35: -22143.7 | H35: -87634.04
A36: CESSAO DE CREDITO
A37: Cessao de Credito | F37: -62000 | H37: -62000
A38: CESSAO DE CREDITO Totale | F38: -62000 | H38: -62000
A39: SAIDAS Totale | B39: -600465.55 | C39: -7863.16 | D39: -20775.58 | E39: -39095.42 | F39: -129688.23 | G39: -41922.08 | H39: -839810.02
A40: Totale complessivo | B40: 70.79 | C40: 864974.19 | D40: 69874.61 | E40: 41847.19 | F40: 623812.34 | G40: 142479.46 | H40: 1743058.6

Sheet Bilancio
A3: Empresa: | B3: SOMBRA RESORT BRASIL Sociedade Unipessoal Ltda
A4: CNPJ: | B4: 43.730.206/0001-80
A5: Insc. Junta Comercial | B5: 24200911503 | C5: 44469
A7: Banco: | B7: Banco do Brasil - Goianinha
A8: Agencia: | B8: 1066-9
A9: Conta: | B9: 48649-3
B11: Ano | C11: Conta Corrente | D11: Investimentos Fundos | E11: Total
B13: 44561 | C13: 0 | D13: 70.79 | E13: =C13+D13 -> 70.79
B15: 44926 | C15: 255109.77 | D15: 609935.21 | E15: =C15+D15 -> 865044.98
B17: 45291 | C17: 0 | D17: 934919.59 | E17: =C17+D17 -> 934919.59
B19: 45657 | C19: 0 | D19: 976766.78 | E19: =C19+D19 -> 976766.78
B21: 46022 | C21: 8856.39 | D21: 1591722.7 | E21: =C21+D21 -> 1600579.1
B23: 46387 | C23: 0 | D23: 0 | E23: =C23+D23 -> 0

Sheet Dati conto Brasile
B3: SOMBRA RESORT BRASIL Sociedad Unipessoal L.T.D.A.
B4: BRASIL
B6: CNPJ: | C6: 43.730.206/0001-80 | D6: 44469
B8: CONTA COM:
B10: BANCO DO BRASIL
B11: AGENCIA | C11: 1066-9
B12: GOIANINHA - R.N. BRASIL
B14: SOMBRA RESORT BRASIL Sociedad Unipessoal L.T.D.A.
B15: C/C | C15: 48649-3
B16: IBAN:
B17: SWIFT: | C17: BRAS BRRJ SBO
